Workbook

Sheet GRE-Remitente
B1: GUIA REMISION ELECTRÓNICA REMITENTE
B2: N° | C2: DATO | D2: NIVEL | E2: CONDICIÓN INFORMÁTICA | F2: TIPO Y LONGITUD | G2: FORMATO | H2: TAG UBL | I2: VALIDACIÓN / CONDICIÓN | J2: TIPO DE RETORNO | K2: CODIGO RETORNO | L2: MENSAJE DE RETORNO | M2: REST o XSL | N2: LISTADOS
B3: - | C3: -
B4: Datos de guía de remisión
B5: 1 | C5: Versión del UBL | D5: Global | E5: M | F5: an..3 | G5: 2.1 | H5: /DespatchAdvice/cbc:UBLVersionID | I5: No existe el Tag UBL o es vacío | J5: ERROR | K5: 2111 | L5: =VLOOKUP(K5,[1]CódigosRetorno!$A$2:$B$1996,2,FALSE) -> El XML no contiene el tag o no existe informacion de UBLVersionID | M5: XSL
I6: El valor del Tag UBL es diferente a '2.1' | J6: ERROR | K6: 2110 | L6: =VLOOKUP(K6,[1]CódigosRetorno!$A$2:$B$1996,2,FALSE) -> UBLVersionID - La versión del UBL no es correcta | M6: XSL
B7: =+B5+1 -> 2 | C7: Versión de la estructura del documento | D7: Global | E7: M | F7: an..3 | G7: 2.0 | H7: /DespatchAdvice/cbc:CustomizationID | I7: No existe el Tag UBL o es vacío | J7: ERROR | K7: 2113 | L7: =VLOOKUP(K7,[1]CódigosRetorno!$A$2:$B$1996,2,FALSE) -> El XML no contiene el tag o no existe informacion de CustomizationID | M7: XSL
I8: El valor del Tag UBL es diferente a '2.0' | J8: ERROR | K8: 2112 | L8: =VLOOKUP(K8,[1]CódigosRetorno!$A$2:$B$1996,2,FALSE) -> CustomizationID - La version del documento no es correcta | M8: XSL
B9: =+B7+1 -> 3 | C9: Numeracion, conformada por serie y Número correlativo | D9: Global | E9: M | F9: an..13 | G9: T###-NNNNNNNN | H9: /DespatchAdvice/cbc:ID | I9: El formato del Tag UBL es diferente a: [T][A-Z0-9]{3}-[0-9]{1,8} | J9: ERROR | K9: 1001 | L9: =VLOOKUP(K9,[1]CódigosRetorno!$A$2:$B$1996,2,FALSE) -> ID - El dato SERIE-CORRELATIVO no cumple con el formato de acuerdo al tipo de comprobante | M9: XSL
I10: El número de serie del Tag UBL es diferente al número de serie del archivo | J10: ERROR | K10: 1035 | L10: =VLOOKUP(K10,[1]CódigosRetorno!$A$2:$B$1996,2,FALSE) -> Numero de Serie del nombre del archivo no coincide con el consignado en el contenido del archivo XML | M10: XSL
I11: El número de documento del Tag UBL es diferente al número de documento del archivo | J11: ERROR | K11: 1036 | L11: =VLOOKUP(K11,[1]CódigosRetorno!$A$2:$B$1996,2,FALSE) -> Número de documento en el nombre del archivo no coincide con el consignado en el contenido del XML | M11: XSL
I12: El valor del Tag UBL se encuentra en el listado con indicador de estado igual a 1 | J12: ERROR | K12: 1033 | L12: =VLOOKUP(K12,[1]CódigosRetorno!$A$2:$B$1996,2,FALSE) -> El comprobante fue registrado previamente con otros datos | M12: REST | N12: Comprobantes de pago electrónico
I13: El valor del Tag UBL se encuentra en el listado con indicador de estado igual a 2 | J13: ERROR | K13: 1032 | L13: =VLOOKUP(K13,[1]CódigosRetorno!$A$2:$B$1996,2,FALSE) -> El comprobante ya esta informado y se encuentra con estado anulado o rechazado | M13: REST | N13: Comprobantes de pago electrónico
B14: =+B9+1 -> 4 | C14: Fecha de emisión | D14: Global | E14: M | F14: an10 | G14: YYYY-MM-DD | H14: /DespatchAdvice/cbc:IssueDate | I14: El valor del Tag UBL no cumple con el formato establecido | J14: ERROR | K14: 3436 | L14: =VLOOKUP(K14,[1]CódigosRetorno!$A$2:$B$1996,2,FALSE) -> El campo de fecha de emision no cumple con el formato establecido | M14: XSL
I15: La diferencia entre la fecha de recepción del XML y el valor del Tag UBL es mayor al límite del listado (1 día) | J15: ERROR | K15: 2108 | L15: =VLOOKUP(K15,[1]CódigosRetorno!$A$2:$B$1996,2,FALSE) -> Presentacion fuera de fecha | M15: REST | N15: Parámetros (004)
I16: El valor del Tag UBL es mayor a la fecha de recepción (TODAY) o es 12/07/2022 | J16: ERROR | K16: 2329 | L16: =VLOOKUP(K16,[1]CódigosRetorno!$A$2:$B$1996,2,FALSE) -> La fecha de emision se encuentra fuera del limite permitido | M16: XSL
B17: =+B14+1 -> 5 | C17: Hora de emisión | D17: Global | E17: M | F17: an8 | G17: hh:mm:ss | H17: /DespatchAdvice/cbc:IssueTime | I17: No existe el Tag UBL | J17: ERROR | K17: 3437 | L17: =VLOOKUP(K17,[1]CódigosRetorno!$A$2:$B$1996,2,FALSE) -> No existe informacion en el campo de hora de emision | M17: XSL
I18: El valor del Tag UBL no cumple con el formato establecido | J18: ERROR | K18: 3438 | L18: =VLOOKUP(K18,[1]CódigosRetorno!$A$2:$B$1996,2,FALSE) -> El campo de hora de emision no cumple con el formato establecido | M18: XSL
B19: =+B17+1 -> 6 | C19: Tipo de documento (Guia) | D19: Global | E19: M | F19: an2 | G19: "09" | H19: /DespatchAdvice/cbc:DespatchAdviceTypeCode | I19: No existe el Tag UBL o es vacío | J19: ERROR | K19: 1050 | L19: =VLOOKUP(K19,[1]CódigosRetorno!$A$2:$B$1996,2,FALSE) -> El XML no contiene informacion en el tag DespatchAdviceTypeCode. | M19: XSL
I20: El valor del Tag UBL es diferente a '09' | J20: ERROR | K20: 1051 | L20: =VLOOKUP(K20,[1]CódigosRetorno!$A$2:$B$1996,2,FALSE) -> DespatchAdviceTypeCode - El valor del tipo de guía es inválido. | M20: XSL
G21: "PE:SUNAT" | H21: @listAgencyName | I21: Si existe el atributo, el valor ingresado es diferente a 'PE:SUNAT' | J21: OBSERV | K21: 4251 | L21: =VLOOKUP(K21,[1]CódigosRetorno!$A$2:$B$1996,2,FALSE) -> El dato ingresado como atributo @listAgencyName es incorrecto. | M21: XSL
G22: "Tipo de Documento" | H22: @listName | I22: Si existe el atributo, el valor ingresado es diferente a 'Tipo de Documento' | J22: OBSERV | K22: 4252 | L22: =VLOOKUP(K22,[1]CódigosRetorno!$A$2:$B$1996,2,FALSE) -> El dato ingresado como atributo @listName es incorrecto. | M22: XSL
G23: "urn:pe:gob:sunat:cpe:see:gem:catalogos:catalogo01" | H23: @listURI | I23: Si existe el atributo, el valor ingresado es diferente a 'urn:pe:gob:sunat:cpe:see:gem:catalogos:catalogo01' | J23: OBSERV | K23: 4253 | L23: =VLOOKUP(K23,[1]CódigosRetorno!$A$2:$B$1996,2,FALSE) -> El dato ingresado como atributo @listURI es incorrecto. | M23: XSL
B24: =+B19+1 -> 7 | C24: Observaciones (Texto) | D24: Global | E24: C | F24: an..250 | H24: /DespatchAdvice/cbc:Note | I24: Si el Tag UBL existe, el formato del Tag UBL es diferente a alfanumérico de hasta 250 caracteres o es vacío (se considera cualquier carácter incluido espacio, no se permite ningún otro 'whitespace character': salto de línea, tab, fin de línea, etc. Tampoco se permite solo espacios en blanco) | J24: OBSERV | K24: 4186 | L24: =VLOOKUP(K24,[1]CódigosRetorno!$A$2:$B$1996,2,FALSE) -> cbc:Note - El campo observaciones supera la cantidad maxima especificada (250 carácteres). | M24: XSL
B25: Datos del Remitente
B26: =B24+1 -> 8 | C26: Tipo y número de documento de identidad del remitente | D26: Global | E26: M | F26: an1 | G26: "6" | H26: /DespatchAdvice/cac:DespatchSupplierParty/cac:Party/cac:PartyIdentification/cbc:ID@schemeID (Tipo de documento de identidad del remitente) | I26: No existe el atributo o es vacío | J26: ERROR | K26: 2678 | L26: =VLOOKUP(K26,[1]CódigosRetorno!$A$2:$B$1996,2,FALSE) -> El XML no contiene el atributo o no existe información del tipo de documento del emisor | M26: XSL
I27: El valor del atributo es diferente a '6' | J27: ERROR | K27: 2511 | L27: =VLOOKUP(K27,[1]CódigosRetorno!$A$2:$B$1996,2,FALSE) -> El tipo de documento no es aceptado. | M27: XSL
G28: "Documento de Identidad" | H28: @schemeName | I28: Si existe el atributo, el valor ingresado es diferente a 'Documento de Identidad' | J28: OBSERV | K28: 4255 | L28: =VLOOKUP(K28,[1]CódigosRetorno!$A$2:$B$1996,2,FALSE) -> El dato ingresado como atributo @schemeName es incorrecto. | M28: XSL
G29: "PE:SUNAT" | H29: @schemeAgencyName | I29: Si existe el atributo, el valor ingresado es diferente a 'PE:SUNAT' | J29: OBSERV | K29: 4256 | L29: =VLOOKUP(K29,[1]CódigosRetorno!$A$2:$B$1996,2,FALSE) -> El dato ingresado como atributo @schemeAgencyName es incorrecto. | M29: XSL
G30: "urn:pe:gob:sunat:cpe:see:gem:catalogos:catalogo06" | H30: @schemeURI | I30: Si existe el atributo, el valor ingresado es diferente a 'urn:pe:gob:sunat:cpe:see:gem:catalogos:catalogo06' | J30: OBSERV | K30: 4257 | L30: =VLOOKUP(K30,[1]CódigosRetorno!$A$2:$B$1996,2,FALSE) -> El dato ingresado como atributo @schemeURI es incorrecto. | M30: XSL
F31: an11 | G31: n11 | H31: /DespatchAdvice/cac:DespatchSupplierParty/cac:Party/cac:PartyIdentification/cbc:ID (Número de documento de identidad del remitente) | I31: El Tag UBL es diferente al RUC del nombre del XML | J31: ERROR | K31: 1034 | L31: =VLOOKUP(K31,[1]CódigosRetorno!$A$2:$B$1996,2,FALSE) -> Número de RUC del nombre del archivo no coincide con el consignado en el contenido del archivo XML | M31: XSL
I32: El valor del Tag UBL tiene un ind_estado diferente '00' en el listado | J32: ERROR | K32: 2010 | L32: =VLOOKUP(K32,[1]CódigosRetorno!$A$2:$B$1996,2,FALSE) -> El contribuyente no esta activo | M32: REST | N32: Contribuyentes
I33: El valor del Tag UBL tiene un ind_condicion diferente a '00' en el listado | J33: ERROR | K33: 2011 | L33: =VLOOKUP(K33,[1]CódigosRetorno!$A$2:$B$1996,2,FALSE) -> El contribuyente no esta habido | M33: REST | N33: Contribuyentes
I34: Se encuentra afecto exclusivamente solo a los tributos Renta de primera categoría, Renta de segunda categoría o Renta de cuarta categoría (no está afecto a ningún otro tributo distinto de los indicados) | J34: ERROR | K34: 3439 | L34: =VLOOKUP(K34,[1]CódigosRetorno!$A$2:$B$1996,2,FALSE) -> El RUC no esta afecto a los tributos autorizados | M34: REST | N34: Afectación
B35: =+B26+1 -> 9 | C35: Apellidos y nombres, denominación o razón social del remitente | D35: Global | E35: M | F35: an..250 | H35: /DespatchAdvice/cac:DespatchSupplierParty/cac:Party/cac:PartyLegalEntity/cbc:RegistrationName | I35: No existe el Tag UBL o es vacío | J35: ERROR | K35: 1037 | L35: =VLOOKUP(K35,[1]CódigosRetorno!$A$2:$B$1996,2,FALSE) -> El XML no contiene el tag o no existe informacion de RegistrationName del emisor del documento | M35: XSL
I36: El formato del Tag UBL es diferente a alfanumérico de hasta 250 caracteres (se considera cualquier carácter incluido espacio, no se permite ningún otro 'whitespace character': salto de línea, tab, fin de línea, etc. Tampoco se permite solo espacios en blanco) | J36: OBSERV | K36: 4338 | L36: =VLOOKUP(K36,[1]CódigosRetorno!$A$2:$B$1996,2,FALSE) -> RegistrationName - El nombre o razon social del emisor no cumple con el estandar | M36: XSL
B37: =B35+1 -> 10 | C37: Entidad emisora de la autorización especial - remitente Número de autorización especial emitido por la entidad - remitente | D37: Global | E37: C | F37: an..50 | H37: /DespatchAdvice/cac:Shipment/cac:Delivery/cac:Despatch/cac:DespatchParty/cac:AgentParty/cac:PartyLegalEntity/cbc:CompanyID (Número de autorización) | I37: Si el Tag UBL existe, el formato del Tag UBL es diferente a alfanumérico de 3 a 50 caracteres (se considera cualquier carácter incluido espacio, no se permite ningún otro 'whitespace character': salto de línea, tab, fin de línea, etc. Tampoco se permite solo espacios en blanco) | J37: OBSERV | K37: 4369 | L37: =VLOOKUP(K37,[1]CódigosRetorno!$A$2:$B$1996,2,FALSE) -> El dato ingresado como numero de autorizacion del Remitente no cumple con el formato establecido | M37: XSL
I38: Si el Tag UBL existe y es diferente de vacío, existe otro cac:PartyLegalEntity | J38: ERROR | K38: 3353 | L38: =VLOOKUP(K38,[1]CódigosRetorno!$A$2:$B$1996,2,FALSE) -> Solo debe consignar un Numero de autorizacion | M38: XSL
F39: an2 | G39: (Catálogo N.° D-37) | H39: /DespatchAdvice/cac:Shipment/cac:Delivery/cac:Despatch/cac:DespatchParty/cac:AgentParty/cac:PartyLegalEntity/cbc:CompanyID@schemeID (Código de entidad autorizadora) | I39: Si existe el atributo y es diferente de vacío, el valor ingresado no se encuentra en el listado | J39: OBSERV | K39: 4395 | L39: =VLOOKUP(K39,[1]CódigosRetorno!$A$2:$B$1996,2,FALSE) -> El Codigo de entidad autorizadora es invalido | M39: XSL | N39: Catálogo (D-37)
I40: Si existe 'Número de autorización' con valor diferente de vacío, no existe el atributo o es vacío | J40: OBSERV | K40: 4394 | L40: =VLOOKUP(K40,[1]CódigosRetorno!$A$2:$B$1996,2,FALSE) -> Debe indicar la entidad autorizadora de la autorizacion especial | M40: XSL
I41: Si existe el atributo y el valor ingresado es diferente de vacío, el 'Número de Autorización' es vacío | J41: OBSERV | K41: 4397 | L41: =VLOOKUP(K41,[1]CódigosRetorno!$A$2:$B$1996,2,FALSE) -> SI existe el Codigo de entidad autorizadora, debe consignar el Numero de autorizacion especial de la empresa | M41: XSL
G42: "Entidad Autorizadora" | H42: @schemeName | I42: Si existe el atributo, el valor ingresado es diferente a 'Entidad Autorizadora' | J42: OBSERV | K42: 4255 | L42: =VLOOKUP(K42,[1]CódigosRetorno!$A$2:$B$1996,2,FALSE) -> El dato ingresado como atributo @schemeName es incorrecto. | M42: XSL
G43: "PE:SUNAT" | H43: @schemeAgencyName | I43: Si existe el atributo, el valor ingresado es diferente a 'PE:SUNAT' | J43: OBSERV | K43: 4256 | L43: =VLOOKUP(K43,[1]CódigosRetorno!$A$2:$B$1996,2,FALSE) -> El dato ingresado como atributo @schemeAgencyName es incorrecto. | M43: XSL
B44: Documento relacionado - incremental
B45: 11 | C45: Tipo de documento (Descripción) | D45: Global | E45: C | F45: an..120 | H45: /DespatchAdvice/cac:AdditionalDocumentReference/cbc:DocumentType | I45: Si existe 'Código del tipo de documento relacionado' y es diferente de vacío, no existe el Tag UBL o es vacío | J45: OBSERV | K45: 4371 | L45: =VLOOKUP(K45,[1]CódigosRetorno!$A$2:$B$1996,2,FALSE) -> El XML no contiene el tag o no existe informacion de la descripcion del tipo de documento relacionado | M45: XSL
I46: Si el Tag UBL existe y es diferente de vacío, no existe 'Código del tipo de documento relacionado' o es vacío | J46: OBSERV | K46: 4410 | L46: =VLOOKUP(K46,[1]CódigosRetorno!$A$2:$B$1996,2,FALSE) -> Si existe descripcion del documento relacionado debe existir informacion del codigo y numero del documento relacionado | M46: XSL
I47: Si el Tag UBL existe y es diferente de vacío, el formato es diferente a alfanumérico de hasta 120 caracteres (se considera cualquier carácter incluido espacio, no se permite ningún otro 'whitespace character': salto de línea, tab, fin de línea, etc. Tampoco se permite solo espacios en blanco) | J47: OBSERV | K47: 4372 | L47: =VLOOKUP(K47,[1]CódigosRetorno!$A$2:$B$1996,2,FALSE) -> La descripcion del tipo de documento relacionado no cumple con el estandar | M47: XSL
B48: =+B45+1 -> 12 | C48: Código del tipo de documento relacionado | D48: Global | E48: C | F48: an2 | G48: (Catálogo N° 61) | H48: /DespatchAdvice/cac:AdditionalDocumentReference/cbc:DocumentTypeCode | I48: Si el Tag UBL existe y es diferente de vacío, el valor del Tag UBL no está en el listado de acuerdo al tipo de guía | J48: ERROR | K48: 2692 | L48: =VLOOKUP(K48,[1]CódigosRetorno!$A$2:$B$1996,2,FALSE) -> El tipo de documento relacionado no es válido | M48: XSL | N48: Catálogo (061)
I49: Si el Tag UBL existe y es diferente de vacío, el 'Número de documento relacionado' es vacío | J49: ERROR | K49: 3403 | L49: =VLOOKUP(K49,[1]CódigosRetorno!$A$2:$B$1996,2,FALSE) -> El XML no contiene el tag o no existe informacion del numero de documento relacionado | M49: XSL
I50: Si el 'Motivo de traslado' es '08' o '09' y no existe un Documento relacionado (cac:AdditionalDocumentReference) con 'Código del tipo de documento relacionado' igual a '50' o '52' | J50: ERROR | K50: 3440 | L50: =VLOOKUP(K50,[1]CódigosRetorno!$A$2:$B$1996,2,FALSE) -> No se ha ingresado el tipo Declaracion Aduanera de Mercancias (DAM) o el Declaracion Simplificada (DS) para el motivo de traslado selecionado | M50: XSL
I51: Si el 'Motivo de traslado' es '08' o '09' y existe un Documento relacionado (cac:AdditionalDocumentReference) con 'Código del tipo de documento relacionado' diferente a '09', '49', '50', '52' y '80' | J51: ERROR | K51: 3445 | L51: =VLOOKUP(K51,[1]CódigosRetorno!$A$2:$B$1996,2,FALSE) -> El tipo de documento relacionado no corresponde para motivo de traslado seleccionado | M51: XSL
I52: Si el 'Motivo de traslado' diferente a '08', '09' y '13' y existe un Documento relacionado (cac:AdditionalDocumentReference) con 'Código del tipo de documento relacionado' igual a '50' o '52' | J52: ERROR | K52: 3445 | L52: =VLOOKUP(K52,[1]CódigosRetorno!$A$2:$B$1996,2,FALSE) -> El tipo de documento relacionado no corresponde para motivo de traslado seleccionado | M52: XSL
I53: Si el Tag UBL existe y es '49' o '80', y no existe el 'Indicador de traslado total de la DAM o la DS' (Falso), no existe ningún 'Bien a trasladar' (cac:DespatchLine) con 'Partida arancelaria' (cac:AdditionalItemProperty con cbc:NameCode igual a '7020') | J53: ERROR | K53: 3352 | L53: =VLOOKUP(K53,[1]CódigosRetorno!$A$2:$B$1996,2,FALSE) -> Si ingreso un documento relacionado tipo "49" (solo en caso de GRE-Remitente) u "80", debe existir al menos un item con Partida arancelaria | M53: XSL
G54: "PE:SUNAT" | H54: @listAgencyName | I54: Si existe el atributo, el valor ingresado es diferente a 'PE:SUNAT' | J54: OBSERV | K54: 4251 | L54: =VLOOKUP(K54,[1]CódigosRetorno!$A$2:$B$1996,2,FALSE) -> El dato ingresado como atributo @listAgencyName es incorrecto. | M54: XSL
G55: "Documento relacionado al transporte" | H55: @listName | I55: Si existe el atributo, el valor ingresado es diferente a 'Documento relacionado al transporte' | J55: OBSERV | K55: 4252 | L55: =VLOOKUP(K55,[1]CódigosRetorno!$A$2:$B$1996,2,FALSE) -> El dato ingresado como atributo @listName es incorrecto. | M55: XSL
G56: "urn:pe:gob:sunat:cpe:see:gem:catalogos:catalogo61" | H56: @listURI | I56: Si existe el atributo, el valor ingresado es diferente a 'urn:pe:gob:sunat:cpe:see:gem:catalogos:catalogo61' | J56: OBSERV | K56: 4253 | L56: =VLOOKUP(K56,[1]CódigosRetorno!$A$2:$B$1996,2,FALSE) -> El dato ingresado como atributo @listURI es incorrecto. | M56: XSL
B57: =B48+1 -> 13 | C57: Número de documento relacionado | D57: Global | E57: C | F57: an..100 | H57: /DespatchAdvice/cac:AdditionalDocumentReference/cbc:ID | I57: Si el valor del Tag UBL es diferente de vacío, el 'Código del tipo de documento relacionado' concatenado con el valor del Tag UBL se repite en el /DespatchAdvice | J57: ERROR | K57: 3340 | L57: =VLOOKUP(K57,[1]CódigosRetorno!$A$2:$B$1996,2,FALSE) -> El documento relacionado al traslado de mercancias se encuentra duplicado | M57: XSL
I58: Si el valor del Tag UBL es diferente de vacío, el 'Código del tipo de documento relacionado' no existe o es vacío | J58: ERROR | K58: 3376 | L58: =VLOOKUP(K58,[1]CódigosRetorno!$A$2:$B$1996,2,FALSE) -> El XML no contiene el tag o no existe informacion del Codigo de tipo de documento relacionado | M58: XSL
I59: Si el 'Código del tipo de documento relacionado' es '01', el formato del Tag UBL es diferente a <Serie>-<Numero> con la siguiente estructura: - [F][A-Z0-9]{3}-[0-9]{1,8} - (E001)-[0-9]{1,8} - [0-9]{1,4}-[0-9]{1,8} El campo <Numero> debe ser mayor a cero | J59: ERROR | K59: 3441 | L59: =VLOOKUP(K59,[1]CódigosRetorno!$A$2:$B$1996,2,FALSE) -> El numero de documento relacionado al traslado de mercancias no cumple con el formato establecido | M59: XSL
I60: Si el 'Código del tipo de documento relacionado' es '03', el formato del Tag UBL es diferente a <Serie>-<Numero> con la siguiente estructura: - [B][A-Z0-9]{3}-[0-9]{1,8} - (EB01)-[0-9]{1,8} - [0-9]{1,4}-[0-9]{1,8} El campo <Numero> debe ser mayor a cero | J60: ERROR | K60: 3441 | L60: =VLOOKUP(K60,[1]CódigosRetorno!$A$2:$B$1996,2,FALSE) -> El numero de documento relacionado al traslado de mercancias no cumple con el formato establecido | M60: XSL
I61: Si el 'Código del tipo de documento relacionado' es '04', el formato del Tag UBL es diferente a <Serie>-<Numero> con la siguiente estructura: - [L][A-Z0-9]{3}-[0-9]{1,8} - (E001)-[0-9]{1,8} - [0-9]{1,4}-[0-9]{1,8} El campo <Numero> debe ser mayor a cero | J61: ERROR | K61: 3441 | L61: =VLOOKUP(K61,[1]CódigosRetorno!$A$2:$B$1996,2,FALSE) -> El numero de documento relacionado al traslado de mercancias no cumple con el formato establecido | M61: XSL
I62: Si el 'Código del tipo de documento relacionado' es '09', el formato del Tag UBL es diferente a <Serie>-<Numero> con la siguiente estructura: - [T][A-Z0-9]{3}-[0-9]{1,8} - (EG07)-[0-9]{1,8} - (EG02)-[0-9]{1,8} El campo <Numero> debe ser mayor a cero | J62: ERROR | K62: 3441 | L62: =VLOOKUP(K62,[1]CódigosRetorno!$A$2:$B$1996,2,FALSE) -> El numero de documento relacionado al traslado de mercancias no cumple con el formato establecido | M62: XSL
I63: Si el 'Código del tipo de documento relacionado' es '12', el formato del Tag UBL es diferente a <Serie>-<Numero> con la siguiente estructura: - [a-zA-Z0-9-]{1,20}-[a-zA-Z0-9-]{1,20} | J63: ERROR | K63: 3441 | L63: =VLOOKUP(K63,[1]CódigosRetorno!$A$2:$B$1996,2,FALSE) -> El numero de documento relacionado al traslado de mercancias no cumple con el formato establecido | M63: XSL
I64: Si el 'Código del tipo de documento relacionado' es '48', el formato del Tag UBL es diferente a <Serie>-<Numero> con la siguiente estructura: - [0-9]{1,4}-[0-9]{1,7} El campo <Numero> debe ser mayor a cero | J64: ERROR | K64: 3441 | L64: =VLOOKUP(K64,[1]CódigosRetorno!$A$2:$B$1996,2,FALSE) -> El numero de documento relacionado al traslado de mercancias no cumple con el formato establecido | M64: XSL
I65: Si el 'Código del tipo de documento relacionado' es '49', el formato del Tag UBL es diferente a numérico hasta 15 dígitos (debe ser mayor a cero) | J65: ERROR | K65: 3441 | L65: =VLOOKUP(K65,[1]CódigosRetorno!$A$2:$B$1996,2,FALSE) -> El numero de documento relacionado al traslado de mercancias no cumple con el formato establecido | M65: XSL
I66: Si el 'Código del tipo de documento relacionado' es '80', el formato del Tag UBL es diferente a numérico hasta 15 dígitos (debe ser mayor a cero) | J66: ERROR | K66: 3441 | L66: =VLOOKUP(K66,[1]CódigosRetorno!$A$2:$B$1996,2,FALSE) -> El numero de documento relacionado al traslado de mercancias no cumple con el formato establecido | M66: XSL
I67: Si el 'Código del tipo de documento relacionado' es '81', el formato del Tag UBL es diferente de alfanumérico de hasta 20 caracteres | J67: ERROR | K67: 3441 | L67: =VLOOKUP(K67,[1]CódigosRetorno!$A$2:$B$1996,2,FALSE) -> El numero de documento relacionado al traslado de mercancias no cumple con el formato establecido | M67: XSL
I68: Si el 'Código del tipo de documento relacionado' es '50' o '52', el formato del Tag UBL es diferente de: - [0-9]{3}-[0-9]{4}-[0-9]{2}-[0-9]{1,6} donde: [0-9]{3}: Código de la Aduana, [0-9]{4}: Año, [0-9]{2} Régimen aduanero, [0-9]{1,6} Correlativo | J68: ERROR | K68: 3441 | L68: =VLOOKUP(K68,[1]CódigosRetorno!$A$2:$B$1996,2,FALSE) -> El numero de documento relacionado al traslado de mercancias no cumple con el formato establecido | M68: XSL
I69: Si el 'Código del tipo de documento relacionado' es '50' y el 'Motivo de traslado' es '08' el formato del Tag UBL es diferente de: - [0-9]{3}-[0-9]{4}-10-[0-9]{1,6} | J69: ERROR | K69: 3441 | L69: =VLOOKUP(K69,[1]CódigosRetorno!$A$2:$B$1996,2,FALSE) -> El numero de documento relacionado al traslado de mercancias no cumple con el formato establecido | M69: XSL
... I73: Si el 'Código del tipo de documento relacionado' es "71", "72", "73", "74", "75", "76", "77" o "78", el formato del Tag UBL es diferente a alfanumérico de hasta 100 caracteres (se considera cualquier carácter, no permite 'whitespace character': espacio, salto de línea, fin de línea, tab, etc.) | J73: ERROR | K73: 3441 | L73: =VLOOKUP(K73,[1]CódigosRetorno!$A$2:$B$1996,2,FALSE) -> El numero de documento relacionado al traslado de mercancias no cumple con el formato establecido | M73: XSL
I74: Si el 'Código de tipo de documento' es '09', el valor del Tag UBL no se encuentra en el listado con estado de 'Baja - por cambio de destinatario' | J74: ERROR | K74: 2536 | L74: =VLOOKUP(K74,[1]CódigosRetorno!$A$2:$B$1996,2,FALSE) -> La serie y numero de la GRE consignada como documento relacionado no se encuentra registrado con baja por cambio de destinatario | M74: REST | N74: Detalle Guia Remisión Electrónica
I75: Si el 'Código de tipo de documento' es '50' o '52', el valor del Tag UBL no se encuentra en el listado | J75: ERROR | K75: 3341 | L75: =VLOOKUP(K75,[1]CódigosRetorno!$A$2:$B$1996,2,FALSE) -> No existe el numero de Declaracion Aduanera de Mercancias (DAM) o el Declaracion Simplificada (DS) | M75: REST | N75: Número de DAM y DS
I76: Si existe más de un 'Documento relacionado' con el 'Código de tipo de documento' igual a '50' o '52', y el motivo de traslado es '08', no coinciden los tipos y números de documento de identidad del importador consignados en dichos documentos. | J76: ERROR | K76: 3394 | L76: =VLOOKUP(K76,[1]CódigosRetorno!$A$2:$B$1996,2,FALSE) -> Si existe mas de una DAM o DS, deben coincidir los tipos y numeros de documento de identidad del importador o exportador consignados en dichos documentos | M76: REST | N76: Detalle de DAM y DS
I77: Si existe más de un 'Documento relacionado' con el 'Código de tipo de documento' igual a '50' o '52', y el motivo de traslado es '09', no coinciden los tipos y números de documento de identidad del exportador consignados en dichos documentos. | J77: ERROR | K77: 3394 | L77: =VLOOKUP(K77,[1]CódigosRetorno!$A$2:$B$1996,2,FALSE) -> Si existe mas de una DAM o DS, deben coincidir los tipos y numeros de documento de identidad del importador o exportador consignados en dichos documentos | M77: REST | N77: Detalle de DAM y DS
I78: Si el 'Código de tipo de documento' es '49' o '80' y se encuentra referenciada en otras GRE - remitente que hayan sido emitidas por el mismo remitente en los últimos 15 días calendario contados a partir de la fecha de recepción de la GRE. | J78: OBSERV | K78: 4432 | L78: =VLOOKUP(K78,[1]CódigosRetorno!$A$2:$B$1996,2,FALSE) -> La Constancia de Deposito ingresada ya ha sido referenciada en otra GRE emitida por el mismo remitente | M78: REST | N78: Detalle Guia Remisión Electrónica
I79: Si el 'Código de tipo de documento' es '49' o '80' y se encuentra referenciada en otras GRE - remitente que hayan sido emitidas por un usuario diferente al remitente o en GRE - transportista, en los últimos 15 días calendario contados a partir de la fecha de recepción de la GRE | J79: ERROR | K79: 3342 | L79: =VLOOKUP(K79,[1]CódigosRetorno!$A$2:$B$1996,2,FALSE) -> La Constancia de Deposito ingresada ya ha sido referenciada en otra GRE emitida | M79: REST | N79: Detalle Guia Remisión Electrónica
I80: Si existe el Tag UBL y el código de tipo de documento es '49' u '80', el valor del Tag UBL no se encuentra en el listado en los últimos 15 días calendario contados a partir de la fecha de recepción de la GRE | J80: OBSERV | K80: 4404 | L80: =VLOOKUP(K80,[1]CódigosRetorno!$A$2:$B$1996,2,FALSE) -> La SUNAT no cuenta con la informacion en los ultimos 15 dias de la Constancia de Deposito en sus sistemas | M80: REST | N80: Constancias de depósito Detracciones / IVAP
I81: Si el 'Código de tipo de documento' es '01', '03' o '04' y la serie no empieza con número, el valor del Tag UBL no se encuentra en el listado para el emisor de documento | J81: OBSERV | K81: 4382 | L81: =VLOOKUP(K81,[1]CódigosRetorno!$A$2:$B$1996,2,FALSE) -> El numero de comprobante consignado como documento relacionado no existe | M81: REST | N81: Comprobantes de pago electrónico
I82: Si el 'Código de tipo de documento' es '01', '03', '04', '09' o '48' y la serie empieza con número, el valor del Tag UBL no se encuentra en el listado para el emisor de documento | J82: ERROR | K82: 3207 | L82: =VLOOKUP(K82,[1]CódigosRetorno!$A$2:$B$1996,2,FALSE) -> Comprobante físico no se encuentra autorizado | M82: REST | N82: Autorizaciones de comprobantes físicos
B83: =B57+1 -> 14 | C83: Número de RUC del emisor del documento relacionado | D83: Global | E83: C | F83: an11 | G83: n11 | H83: /DespatchAdvice/cac:AdditionalDocumentReference/cac:IssuerParty/cac:PartyIdentification/cbc:ID (Número de documento del emisor del documento) | I83: Si el 'Código del tipo de documento relacionado' es '01', '03', '04', '09', '12', '48', no existe el Tag UBL o es vacío | J83: ERROR | K83: 3380 | L83: =VLOOKUP(K83,[1]CódigosRetorno!$A$2:$B$1996,2,FALSE) -> Debe consignar el RUC del emisor del documento relacionado | M83: XSL
I84: Si el Tag UBL existe y es diferente de vacío, y el 'Motivo de traslado' es '01', '03' y el 'Código del tipo de documento relacionado' es '01', '03', '12', el valor del Tag UBL es diferente al RUC del remitente | J84: ERROR | K84: 3381 | L84: =VLOOKUP(K84,[1]CódigosRetorno!$A$2:$B$1996,2,FALSE) -> El RUC del emisor del documento relacionado no corresponde | M84: XSL
I85: Si el Tag UBL existe y es diferente de vacío y el 'Código del tipo de documento relacionado' es '09', el valor del Tag UBL es diferente al RUC del remitente | J85: ERROR | K85: 3381 | L85: =VLOOKUP(K85,[1]CódigosRetorno!$A$2:$B$1996,2,FALSE) -> El RUC del emisor del documento relacionado no corresponde | M85: XSL
I86: Si el Tag UBL existe y es diferente de vacío, y el 'Motivo de traslado' es '02' y el 'Código del tipo de documento relacionado' es '04', '48' el valor del Tag UBL es diferente al RUC del remitente | J86: ERROR | K86: 3381 | L86: =VLOOKUP(K86,[1]CódigosRetorno!$A$2:$B$1996,2,FALSE) -> El RUC del emisor del documento relacionado no corresponde | M86: XSL
I87: Si el Tag UBL existe y es diferente de vacío, y el 'Motivo de traslado' es '06' y el 'Código del tipo de documento relacionado' es '01', '03', '12', el valor del Tag UBL es diferente al RUC del destinatario | J87: ERROR | K87: 3381 | L87: =VLOOKUP(K87,[1]CódigosRetorno!$A$2:$B$1996,2,FALSE) -> El RUC del emisor del documento relacionado no corresponde | M87: XSL
I88: Si el Tag UBL existe y es diferente de vacío, el valor del Tag UBL es diferente de numérico de 11 dígitos | J88: ERROR | K88: 3409 | L88: =VLOOKUP(K88,[1]CódigosRetorno!$A$2:$B$1996,2,FALSE) -> El Numero de RUC no cumple con el formato establecido | M88: XSL
I89: Si el Tag UBL existe y es diferente de vacío, el valor del Tag UBL no existe en el listado | J89: ERROR | K89: 3408 | L89: =VLOOKUP(K89,[1]CódigosRetorno!$A$2:$B$1996,2,FALSE) -> El Numero de RUC del emisor del documento relacionado no existe | M89: REST | N89: Contribuyentes
F90: an1 | G90: (Catálogo N.° 06) | H90: /DespatchAdvice/cac:AdditionalDocumentReference/cac:IssuerParty/cac:PartyIdentification/cbc:ID@schemeID (Tipo de documento de identidad del emisor del documento relacionado) | I90: Si el 'Código del tipo de documento relacionado' es '01', '03', '04', '09', '12', '48', el atributo del Tag UBL no existe o es diferente a 6 (RUC) | J90: ERROR | K90: 3382 | L90: =VLOOKUP(K90,[1]CódigosRetorno!$A$2:$B$1996,2,FALSE) -> El Tipo de documento del emisor del documento relacionado debe ser Numero de RUC | M90: XSL
G91: "Documento de Identidad" | H91: @schemeName | I91: Si existe el atributo, el valor ingresado es diferente a 'Documento de Identidad' | J91: OBSERV | K91: 4255 | L91: =VLOOKUP(K91,[1]CódigosRetorno!$A$2:$B$1996,2,FALSE) -> El dato ingresado como atributo @schemeName es incorrecto. | M91: XSL
G92: "PE:SUNAT" | H92: @schemeAgencyName | I92: Si existe el atributo, el valor ingresado es diferente a 'PE:SUNAT' | J92: OBSERV | K92: 4256 | L92: =VLOOKUP(K92,[1]CódigosRetorno!$A$2:$B$1996,2,FALSE) -> El dato ingresado como atributo @schemeAgencyName es incorrecto. | M92: XSL
G93: "urn:pe:gob:sunat:cpe:see:gem:catalogos:catalogo06" | H93: @schemeURI | I93: Si existe el atributo, el valor ingresado es diferente a 'urn:pe:gob:sunat:cpe:see:gem:catalogos:catalogo06' | J93: OBSERV | K93: 4257 | L93: =VLOOKUP(K93,[1]CódigosRetorno!$A$2:$B$1996,2,FALSE) -> El dato ingresado como atributo @schemeURI es incorrecto. | M93: XSL
B94: Datos del Destinatario
B95: =B83+1 -> 15 | C95: Tipo y número de documento de identidad del destinatario | D95: Global | E95: M | F95: an1 | G95: (Catálogo N° 06) | H95: /DespatchAdvice/cac:DeliveryCustomerParty/cac:Party/cac:PartyIdentification/cbc:ID@schemeID | I95: Si el 'Número de documento de identidad del destinatario' es diferente de vacío, no existe el atributo o es vacío | J95: ERROR | K95: 2759 | L95: =VLOOKUP(K95,[1]CódigosRetorno!$A$2:$B$1996,2,FALSE) -> El XML no contiene el atributo o no existe información del tipo de documento del destinatario. | M95: XSL | N95: -
I96: Si el atributo existe y es diferente de vacío, el valor del Tag UBL no está en el listado | J96: ERROR | K96: 2760 | L96: =VLOOKUP(K96,[1]CódigosRetorno!$A$2:$B$1996,2,FALSE) -> El valor ingresado como tipo de documento del destinatario es incorrecto. | M96: XSL | N96: Catálogo (006)
I97: Si 'Motivo de traslado' es igual a '06' o '17', el valor del atributo es diferente de '6' | J97: ERROR | K97: 3417 | L97: =VLOOKUP(K97,[1]CódigosRetorno!$A$2:$B$1996,2,FALSE) -> Para el motivo de traslado 06 y 17 el tipo de documento de identidad del destinatario debe ser 6-RUC | M97: XSL
G98: "Documento de Identidad" | H98: @schemeName | I98: Si existe el atributo, el valor ingresado es diferente a 'Documento de Identidad' | J98: OBSERV | K98: 4255 | L98: =VLOOKUP(K98,[1]CódigosRetorno!$A$2:$B$1996,2,FALSE) -> El dato ingresado como atributo @schemeName es incorrecto. | M98: XSL
G99: "PE:SUNAT" | H99: @schemeAgencyName | I99: Si existe el atributo, el valor ingresado es diferente a 'PE:SUNAT' | J99: OBSERV | K99: 4256 | L99: =VLOOKUP(K99,[1]CódigosRetorno!$A$2:$B$1996,2,FALSE) -> El dato ingresado como atributo @schemeAgencyName es incorrecto. | M99: XSL
G100: "urn:pe:gob:sunat:cpe:see:gem:catalogos:catalogo06" | H100: @schemeURI | I100: Si existe el atributo, el valor ingresado es diferente a 'urn:pe:gob:sunat:cpe:see:gem:catalogos:catalogo06' | J100: OBSERV | K100: 4257 | L100: =VLOOKUP(K100,[1]CódigosRetorno!$A$2:$B$1996,2,FALSE) -> El dato ingresado como atributo @schemeURI es incorrecto. | M100: XSL
F101: an..15 | H101: /DespatchAdvice/cac:DeliveryCustomerParty/cac:Party/cac:PartyIdentification/cbc:ID | I101: Si no existe el Tag UBL o es vacío | J101: ERROR | K101: 2757 | L101: =VLOOKUP(K101,[1]CódigosRetorno!$A$2:$B$1996,2,FALSE) -> El XML no contiene el tag o no existe información del número de documento de identidad del destinatario. | M101: XSL
I102: Si 'Motivo del traslado' es '01', '03', '05', '06', '09', '14' y '17', el 'Tipo y Número de documento de identidad del destinatario' es igual al 'Tipo y Número de documento de identidad del remitente' | J102: ERROR | K102: 2555 | L102: =VLOOKUP(K102,[1]CódigosRetorno!$A$2:$B$1996,2,FALSE) -> Destinatario no debe ser igual al remitente. | M102: XSL
I103: Si 'Motivo del traslado' es '02', '04' y '07', el 'Tipo y Número de documento de identidad del destinatario' es diferente al 'Tipo y Número de documento de identidad del remitente' | J103: ERROR | K103: 2554 | L103: =VLOOKUP(K103,[1]CódigosRetorno!$A$2:$B$1996,2,FALSE) -> Para el motivo de traslado ingresado el Destinatario debe ser igual al remitente. | M103: XSL
...

Sheet TXT-JSON-GRE-Remitente
B2: GUIA REMISION REMITENTE
B3: Archivo texto: RRRRRRRRRRR-09-TXXX-99999999.TXT
B4: JSON: GRR
B5: Archivo Texto Orden | C5: Archivo JSON - Atributo | D5: DATO | E5: CONDICIÓN INFORMÁTICA | F5: TIPO Y LONGITUD | G5: FORMATO | H5: TAG UBL
B6: Archivo: Cabecera (RRRRRRRRRRR-09-TXXX-999999999.GRR)
B7: Datos de cabecera
B8: 1 | D8: Primera columna de la fila TXT | E8: M | F8: an3 | G8: GRR
B9: 2 | C9: nroCdpSwf | D9: Numeracion, conformada por serie y Número correlativo | E9: M | F9: an..13 | G9: T###-NNNNNNNN | H9: /DespatchAdvice/cbc:ID
B10: 3 | C10: fecEmision | D10: Fecha de emisión | E10: M | F10: an..10 | G10: YYYY-MM-DD | H10: /DespatchAdvice/cbc:IssueDate
B11: 4 | C11: horEmision | D11: Hora de Emisión | E11: M | F11: an8 | G11: HH:MM:SS | H11: /DespatchAdvice/cbc:IssueTime
B12: 5 | C12: tipCdpSwf | D12: Tipo de documento (Guia) | E12: M | F12: an2 | G12: "09" | H12: /DespatchAdvice/cbc:DespatchAdviceTypeCode
B13: 6 | C13: obsGuia | D13: Observaciones (Texto) | E13: C | F13: an..250 | H13: /DespatchAdvice/cbc:Note
B14: Datos del Remitente
B15: 7 | C15: tipDocuRemitenteSwf | D15: Tipo de documento de identidad del remitente | E15: M | F15: an1 | G15: "6" | H15: /DespatchAdvice/cac:DespatchSupplierParty/cac:Party/cac:PartyIdentification/cbc:ID@schemeID
B16: 8 | C16: nroRucRemitenteSwf | D16: Número de documento de identidad del remitente | E16: M | F16: an11 | G16: n11 | H16: /DespatchAdvice/cac:DespatchSupplierParty/cac:Party/cac:PartyIdentification/cbc:ID
B17: 9 | C17: razonSocialRemitenteSwf | D17: Apellidos y nombres, denominación o razón social del remitente | E17: M | F17: an..250 | H17: /DespatchAdvice/cac:DespatchSupplierParty/cac:Party/cac:PartyLegalEntity/cbc:RegistrationName
B18: 10 | C18: nroAutorizacionRemitenteSwf | D18: Entidad emisora de la autorización especial - remitente Número de autorización especial emitido por la entidad - remitente (Número de autorización) | E18: C | F18: an..50 | H18: /DespatchAdvice/cac:Shipment/cac:Delivery/cac:Despatch/cac:DespatchParty/cac:AgentParty/cac:PartyLegalEntity/cbc:CompanyID
B19: 11 | C19: codEntidadAutorizadoraRemitenteSwf | D19: Entidad emisora de la autorización especial - remitente Número de autorización especial emitido por la entidad - remitente (Código de entidad autorizadora) | E19: C | F19: an2 | G19: (Catálogo N.° D-37) | H19: /DespatchAdvice/cac:Shipment/cac:Delivery/cac:Despatch/cac:DespatchParty/cac:AgentParty/cac:PartyLegalEntity/cbc:CompanyID@schemeID
B20: Datos del Destinatario
B21: 12 | C21: tipDocDestinatario | D21: Tipo de documento de identidad del destinatario | E21: M | F21: an1 | G21: (Catálogo N° 06) | H21: /DespatchAdvice/cac:DeliveryCustomerParty/cac:Party/cac:PartyIdentification/cbc:ID@schemeID
B22: 13 | C22: numDocDestinatario | D22: Número de documento de identidad del destinatario | E22: M | F22: an..15 | H22: /DespatchAdvice/cac:DeliveryCustomerParty/cac:Party/cac:PartyIdentification/cbc:ID
B23: 14 | C23: rznSocialDestinatario | D23: Apellidos y nombres, denominación o razón social del destinatario | E23: M | F23: an..250 | H23: /DespatchAdvice/cac:DeliveryCustomerParty/cac:Party/cac:PartyLegalEntity/cbc:RegistrationName
B24: Datos del Proveedor
B25: 15 | C25: tipDocProveedor | D25: Tipo de documento de identidad del proveedor | E25: C | F25: an1 | G25: (Catálogo N° 06) | H25: /DespatchAdvice/cac:SellerSupplierParty/cac:Party/cac:PartyIdentification/cbc:ID@schemeID
B26: 16 | C26: numDocProveedor | D26: Número de documento de identidad del proveedor | E26: C | F26: an..15 | H26: /DespatchAdvice/cac:SellerSupplierParty/cac:Party/cac:PartyIdentification/cbc:ID
B27: 17 | C27: rznSociaProveedor | D27: Apellidos y nombres, denominación o razón social del proveedor | E27: C | F27: an..250 | H27: /DespatchAdvice/cac:SellerSupplierParty/cac:Party/cac:PartyLegalEntity/cbc:RegistrationName
B28: Datos del Comprador
B29: 18 | C29: tipDocComprador | D29: Tipo de documento de identidad del comprador | E29: C | F29: an1 | G29: (Catálogo N° 06) | H29: /DespatchAdvice/cac:BuyerCustomerParty/cac:Party/cac:PartyIdentification/cbc:ID@schemeID
B30: 19 | C30: numDocComprador | D30: Número de documento de identidad del comprador | E30: C | F30: an..15 | H30: /DespatchAdvice/cac:BuyerCustomerParty/cac:Party/cac:PartyIdentification/cbc:ID
B31: 20 | C31: rznSocialComprador | D31: Apellidos y nombres, denominación o razón social del comprador | E31: C | F31: an..250 | H31: /DespatchAdvice/cac:BuyerCustomerParty/cac:Party/cac:PartyLegalEntity/cbc:RegistrationName
B33: Archivo: Detalle (RRRRRRRRRRR-09-TXXX-999999999.ENV)
B34: Datos del envío
B35: 1 | D35: Primera columna de la fila TXT | E35: M | F35: an3 | G35: ENV
B36: 2 | C36: motTrasladoDatosEnvio | D36: Motivo del traslado | E36: M | F36: an2 | G36: (Catálogo N.° 20) | H36: /DespatchAdvice/cac:Shipment/cbc:HandlingCode
B37: 3 | C37: desMotivoTrasladoDatosEnvio | D37: Descripción de motivo de traslado | E37: C | F37: an..100 | H37: /DespatchAdvice/cac:Shipment/cbc:HandlingInstructions
B38: 4 | C38: psoBrutoTotalBienesDatosEnvio | D38: Peso bruto total de los ítems seleccionados (en KGM) | E38: C | F38: an..16 | G38: n(12,3) | H38: /DespatchAdvice/cac:Shipment/cbc:NetWeightMeasure
B39: 5 | C39: uniMedidaPesoBrutoBienesDatosEnvio | D39: Unidad de medida del peso bruto total de los items seleccionados | E39: C | F39: an3 | G39: (Catálogo N.° 03) "KGM" Kilogramos | H39: /DespatchAdvice/cac:Shipment/cbc:NetWeightMeasure@unitCode
B40: 6 | C40: sustentoDifPesoDatosEnvio | D40: Sustento de la diferencia del Peso bruto total de la carga respecto al peso de los ítems seleccionados | E40: C | F40: an..250 | H40: /DespatchAdvice/cac:Shipment/cbc:Information
B41: 7 | C41: psoBrutoTotalCargaDatosEnvio | D41: Peso bruto total de la carga | E41: M | F41: an..16 | G41: n(12,3) | H41: /DespatchAdvice/cac:Shipment/cbc:GrossWeightMeasure
B42: 8 | C42: uniMedidaPesoBrutoDatosEnvio | D42: Unidad de medida del peso bruto | E42: M | F42: an3 | G42: (Catálogo N.° 03) "KGM" Kilogramos "TNE" Toneladas | H42: /DespatchAdvice/cac:Shipment/cbc:GrossWeightMeasure@unitCode
B43: 9 | C43: numBultosDatosEnvio | D43: Número de Bultos o Pallets | E43: C | F43: an..6 | G43: n..6 | H43: /DespatchAdvice/cac:Shipment/cbc:TotalTransportHandlingUnitQuantity
B44: 10 | C44: numContenedor1 | D44: Número de contenedor 1 | E44: C | F44: an..11 | G44: - | H44: /DespatchAdvice/cac:Shipment/cac:TransportHandlingUnit/cac:Package/cbc:ID
B45: 11 | C45: numPrecinto1 | D45: Número de precinto 1 | E45: C | F45: an..20 | H45: /DespatchAdvice/cac:Shipment/cac:TransportHandlingUnit/cac:Package/cbc:TraceID
B46: 12 | C46: numContenedor2 | D46: Número de contenedor 2 | E46: C | F46: an..11 | G46: - | H46: /DespatchAdvice/cac:Shipment/cac:TransportHandlingUnit/cac:Package/cbc:ID
B47: 13 | C47: numPrecinto2 | D47: Número de precinto 2 | E47: C | F47: an..20 | H47: /DespatchAdvice/cac:Shipment/cac:TransportHandlingUnit/cac:Package/cbc:TraceID
B48: 14 | C48: modTrasladoDatosEnvio | D48: Modalidad de traslado | E48: M | F48: an2 | G48: (Catálogo N.° 18) | H48: /DespatchAdvice/cac:Shipment/cac:ShipmentStage/cbc:TransportModeCode
B49: 15 | C49: fecInicioTrasladoDatosEnvio | D49: Fecha Inicio de traslado | E49: C | F49: an10 | G49: YYYY-MM-DD | H49: /DespatchAdvice/cac:Shipment/cac:ShipmentStage/cac:TransitPeriod/cbc:StartDate
B50: 16 | C50: fecEntregaTransportistaDatosEnvio | D50: Fecha de entrega de bienes al transportista | E50: C | F50: an10 | G50: YYYY-MM-DD | H50: /DespatchAdvice/cac:Shipment/cac:ShipmentStage/cac:TransitPeriod/cbc:StartDate
B51: 17 | C51: indTransbordoProgramado | D51: Indicador de Transbordo Programado | E51: C | F51: an..50 | G51: "SUNAT_Envio_IndicadorTransbordoProgramado" | H51: /DespatchAdvice/cac:Shipment/cbc:SpecialInstructions
B52: 18 | C52: indTrasladoVehCatM1oL | D52: Indicador de traslado en vehículos de categoría M1 o L | E52: C | F52: an..50 | G52: "SUNAT_Envio_IndicadorTrasladoVehiculoM1L" | H52: /DespatchAdvice/cac:Shipment/cbc:SpecialInstructions
B53: 19 | C53: indRetornoVehiculoEnvasesEmbalajes | D53: Indicador de retorno de vehículo con envases o embalajes vacíos | E53: C | F53: an..50 | G53: "SUNAT_Envio_IndicadorRetornoVehiculoEnvaseVacio" | H53: /DespatchAdvice/cac:Shipment/cbc:SpecialInstructions
B54: 20 | C54: indRetornoVehiculoVacio | D54: Indicador de retorno de vehículo vacío | E54: C | F54: an..50 | G54: "SUNAT_Envio_IndicadorRetornoVehiculoVacio" | H54: /DespatchAdvice/cac:Shipment/cbc:SpecialInstructions
B55: 21 | C55: indTrasladoTotalDAMoDS | D55: Indicador de traslado total de la DAM o la DS | E55: C | F55: an..50 | G55: "SUNAT_Envio_IndicadorTrasladoTotalDAMoDS" | H55: /DespatchAdvice/cac:Shipment/cbc:SpecialInstructions
B56: 22 | C56: indRegistroVehiculoConductor | D56: Indicador de registro de vehículos y conductores del transportista (de acuerdo con el último párrafo del numeral 3.1. del artículo 3) de la RS N° 255-2015-SUNAT) | E56: C | F56: an..50 | G56: "SUNAT_Envio_IndicadorVehiculoConductoresTransp" | H56: /DespatchAdvice/cac:Shipment/cbc:SpecialInstructions
B57: 23 | C57: tipEventoDatosEnvio | D57: Tipo de evento | E57: C | F57: an1 | G57: 1-Transbordo no programado 2-Imposibilidad arribo 3-Imposibilidad entrega | H57: /DespatchAdvice/cac:Shipment/cac:ShipmentStage/cac:TransportEvent/cbc:TransportEventTypeCode
B59: Archivo: Detalle (RRRRRRRRRRR-09-TXXX-999999999.TTA)
B60: Datos del Transportista
B61: 1 | D61: Primera columna de la fila TXT | E61: M | F61: an3 | G61: TTA
B62: 2 | C62: tipDocTransportista | D62: Tipo de documento de identidad | E62: C | F62: an1 | G62: "6" | H62: /DespatchAdvice/cac:Shipment/cac:ShipmentStage/cac:CarrierParty/cac:PartyIdentification/cbc:ID@schemeID
B63: 3 | C63: numDocTransportista | D63: Número de RUC | E63: C | F63: an11 | G63: n11 | H63: /DespatchAdvice/cac:Shipment/cac:ShipmentStage/cac:CarrierParty/cac:PartyIdentification/cbc:ID
B64: 4 | C64: nomTransportista | D64: Apellidos y Nombres o denominación o razón social del transportista | E64: C | F64: an..250 | H64: /DespatchAdvice/cac:Shipment/cac:ShipmentStage/cac:CarrierParty/cac:PartyLegalEntity/cbc:RegistrationName
B65: 5 | C65: numeroRegistroMTCTransportista | D65: Número de Registro MTC | E65: C | F65: an..20 | H65: /DespatchAdvice/cac:Shipment/cac:ShipmentStage/cac:CarrierParty/cac:PartyLegalEntity/cbc:CompanyID
B66: 6 | C66: numAutorizacionTransportista | D66: Entidad emisora de la autorización especial - transportista Número de autorización especial emitido por la entidad - transportista (Número de autorización) | E66: C | F66: an..50 | H66: /DespatchAdvice/cac:Shipment/cac:ShipmentStage/cac:CarrierParty/cac:AgentParty/cac:PartyLegalEntity/cbc:CompanyID
B67: 7 | C67: codEntidadAutorizadoraTransportista | D67: Entidad emisora de la autorización especial - transportista Número de autorización especial emitido por la entidad - transportista (Código de entidad autorizadora) | E67: C | F67: an2 | G67: (Catálogo N.° D-37) | H67: /DespatchAdvice/cac:Shipment/cac:ShipmentStage/cac:CarrierParty/cac:AgentParty/cac:PartyLegalEntity/cbc:CompanyID@schemeID
B69: Archivo: Detalle (RRRRRRRRRRR-09-TXXX-999999999.VPS)
B70: Vehiculo Principal | H70: Principal | I70: Secundario
B71: Vehiculos Secundarios Incremental hasta 2
B72: 1 | D72: Primera columna de la fila TXT | E72: M | F72: an3 | G72: VPS
B73: 2 | C73: tipVehiculo | D73: Tipo de vehiculo: Principal / Secundario | G73: Principal Secundario
B74: 3 | C74: numPlacaVehículoPrincipal | D74: Número de placa del vehículo | E74: C | F74: an..8 | H74: /DespatchAdvice/cac:Shipment/cac:TransportHandlingUnit/cac:TransportEquipment/cbc:ID | I74: /DespatchAdvice/cac:Shipment/cac:TransportHandlingUnit/cac:TransportEquipment/cac:AttachedTransportEquipment/cbc:ID
B75: 4 | C75: tarjetaUnicaCirculacionElecPrincipal | D75: Tarjeta Única de Circulación Electrónica o Certificado de Habilitación vehicular | E75: C | F75: an..15 | H75: /DespatchAdvice/cac:Shipment/cac:TransportHandlingUnit/cac:TransportEquipment/cac:ApplicableTransportMeans/cbc:RegistrationNationalityID | I75: /DespatchAdvice/cac:Shipment/cac:TransportHandlingUnit/cac:TransportEquipment/cac:AttachedTransportEquipment/cac:ApplicableTransportMeans/cbc:RegistrationNationalityID
B76: 5 | C76: numAutorizacionPrincipal | D76: Entidad emisora de la autorización especial - vehículo principal Número de autorización especial del vehículo emitido por la entidad - vehículo principal (Número de autorización) | E76: C | F76: an..50 | H76: /DespatchAdvice/cac:Shipment/cac:TransportHandlingUnit/cac:TransportEquipment/cac:ShipmentDocumentReference/cbc:ID | I76: /DespatchAdvice/cac:Shipment/cac:TransportHandlingUnit/cac:TransportEquipment/cac:AttachedTransportEquipment/cac:ShipmentDocumentReference/cbc:ID
B77: 6 | C77: codEntidadEmisoraPrincipal | D77: Entidad emisora de la autorización especial - vehículo principal Número de autorización especial del vehículo emitido por la entidad - vehículo principal (Código de entidad emisora) | E77: C | F77: an2 | G77: (Catálogo N.° D-37) | H77: /DespatchAdvice/cac:Shipment/cac:TransportHandlingUnit/cac:TransportEquipment/cac:ShipmentDocumentReference/cbc:ID@schemeID | I77: /DespatchAdvice/cac:Shipment/cac:TransportHandlingUnit/cac:TransportEquipment/cac:AttachedTransportEquipment/cac:ShipmentDocumentReference/cbc:ID@schemeID
B79: Archivo: Detalle (RRRRRRRRRRR-09-TXXX-999999999.CON)
B80: Conductor principal
B81: Conductores secundarios - Incremental hasta 2 | H81: Principal | I81: Secundario
B82: 1 | D82: Primera columna de la fila TXT | E82: M | F82: an3 | G82: CON
B83: 2 | C83: tipConductor | D83: Tipo de Conductor | E83: C | F83: an9 | G83: Principal Secundario | H83: /DespatchAdvice/cac:Shipment/cac:ShipmentStage/cac:DriverPerson/cbc:JobTitle | I83: /DespatchAdvice/cac:Shipment/cac:ShipmentStage/cac:DriverPerson/cbc:JobTitle
B84: 3 | C84: tipDocumentoConductor | D84: Tipo de documento de identidad del conductor | E84: C | F84: an1 | G84: (Catálogo N° 06) | H84: /DespatchAdvice/cac:Shipment/cac:ShipmentStage/cac:DriverPerson/cbc:ID@schemeID | I84: /DespatchAdvice/cac:Shipment/cac:ShipmentStage/cac:DriverPerson/cbc:ID@schemeID
B85: 4 | C85: numDocumentoConductor | D85: Número de documento de identidad del conductor | E85: C | F85: an..15 | H85: /DespatchAdvice/cac:Shipment/cac:ShipmentStage/cac:DriverPerson/cbc:ID | I85: /DespatchAdvice/cac:Shipment/cac:ShipmentStage/cac:DriverPerson/cbc:ID
B86: 5 | C86: nombresConductor | D86: Apellidos y nombres del conductor (Nombres) | E86: C | F86: an..250 | H86: /DespatchAdvice/cac:Shipment/cac:ShipmentStage/cac:DriverPerson/cbc:FirstName | I86: /DespatchAdvice/cac:Shipment/cac:ShipmentStage/cac:DriverPerson/cbc:FirstName
B87: 6 | C87: apellidosConductor | D87: Apellidos y nombres del conductor (Apellidos) | E87: C | F87: an..250 | H87: /DespatchAdvice/cac:Shipment/cac:ShipmentStage/cac:DriverPerson/cbc:FamilyName | I87: /DespatchAdvice/cac:Shipment/cac:ShipmentStage/cac:DriverPerson/cbc:FamilyName
B88: 7 | C88: numLicenciaConducir | D88: Número de licencia de conducir | E88: C | F88: an..10 | H88: /DespatchAdvice/cac:Shipment/cac:ShipmentStage/cac:DriverPerson/cac:IdentityDocumentReference/cbc:ID | I88: /DespatchAdvice/cac:Shipment/cac:ShipmentStage/cac:DriverPerson/cac:IdentityDocumentReference/cbc:ID
B90: Archivo: Detalle (RRRRRRRRRRR-09-TXXX-999999999.PLL)
B91: Dirección del punto de partida
B92: Dirección del punto de llegada | H92: Partida | I92: Llegada
B93: 1 | D93: Primera columna de la fila TXT | E93: M | F93: an3 | G93: PLL
B94: 2 | C94: tipDireccionPartidaLlegada | D94: Tipo de direcciondel Punto: Partida / Llegada | G94: Partida Llegada
B95: 3 | C95: ubiPartidaLlegada | D95: Ubigeo de Partida / Llegada | E95: M | F95: an6 | G95: (Catálogo N° 13) | H95: /DespatchAdvice/cac:Shipment/cac:Delivery/cac:Despatch/cac:DespatchAddress/cbc:ID | I95: /DespatchAdvice/cac:Shipment/cac:Delivery/cac:DeliveryAddress/cbc:ID
B96: 4 | C96: dirPartidaLlegada | D96: Dirección completa y detallada de Partida / Llegada | E96: M | F96: an..500 | H96: /DespatchAdvice/cac:Shipment/cac:Delivery/cac:Despatch/cac:DespatchAddress/cac:AddressLine/cbc:Line | I96: /DespatchAdvice/cac:Shipment/cac:Delivery/cac:DeliveryAddress/cac:AddressLine/cbc:Line
B97: 5 | C97: longitudGeorreferenciaPartidaLlegada | D97: Punto de georreferencia de Partida / Llegada (Longitud) | E97: C | F97: an..13 | G97: n(3,8) | H97: /DespatchAdvice/cac:Shipment/cac:Delivery/cac:Despatch/cac:DespatchAddress/cac:LocationCoordinate/cbc:LatitudeDegreesMeasure | I97: /DespatchAdvice/cac:Shipment/cac:Delivery/cac:DeliveryAddress/cac:LocationCoordinate/cbc:LatitudeDegreesMeasure
B98: 6 | C98: latitudGeorreferenciaPartidaLlegada | D98: Punto de georreferencia de Partida / Llegada (Latitud) | E98: C | F98: an..13 | G98: n(3,8) | H98: /DespatchAdvice/cac:Shipment/cac:Delivery/cac:Despatch/cac:DespatchAddress/cac:LocationCoordinate/cbc:LongitudeDegreesMeasure | I98: /DespatchAdvice/cac:Shipment/cac:Delivery/cac:DeliveryAddress/cac:LocationCoordinate/cbc:LongitudeDegreesMeasure
B99: 7 | C99: rucAsociadoPartidaLlegada | D99: Número de RUC asociado al punto de Partida / Llegada | E99: C | F99: an11 | G99: n11 | H99: /DespatchAdvice/cac:Shipment/cac:Delivery/cac:Despatch/cac:DespatchAddress/cbc:AddressTypeCode@listID | I99: /DespatchAdvice/cac:Shipment/cac:Delivery/cac:DeliveryAddress/cbc:AddressTypeCode@listID
B100: 8 | C100: codEstablecimientoPartidaLlegada | D100: Código de establecimiento de punto de Partida / Llegada | E100: C | F100: an4 | G100: n4 | H100: /DespatchAdvice/cac:Shipment/cac:Delivery/cac:Despatch/cac:DespatchAddress/cbc:AddressTypeCode | I100: /DespatchAdvice/cac:Shipment/cac:Delivery/cac:DeliveryAddress/cbc:AddressTypeCode
B102: Archivo: Detalle (RRRRRRRRRRR-09-TXXX-999999999.EPA)
B103: Puerto o Aeropuerto de embarque/desembarque
B104: 1 | D104: Primera columna de la fila TXT | E104: M | F104: an3 | G104: EPA
B105: 2 | C105: codPuertoAeropuerto | D105: Código del puerto o aeropuerto | E105: C | F105: an3 | G105: (Catálogo N° 63) | H105: /DespatchAdvice/cac:Shipment/cac:FirstArrivalPortLocation/cbc:ID
B106: 3 | C106: tipLocacionCodPuertoAeropuerto | D106: Código del puerto o aeropuerto (Tipo de locación) | E106: C | F106: an1 | G106: 1 - Puerto 2 - Aeropuerto | H106: /DespatchAdvice/cac:Shipment/cac:FirstArrivalPortLocation/cbc:LocationTypeCode
B107: 4 | C107: nombrePuertoAeropuerto | D107: Nombre del puerto o aeropuerto | E107: C | G107: an..200 | H107: /DespatchAdvice/cac:Shipment/cac:FirstArrivalPortLocation/cbc:Name
...

Sheet GRE-R-TXT
A1: 1 | B1: 2 | C1: 3 | D1: 4 | E1: 5 | F1: 6 | G1: 7 | H1: 8 | I1: 9 | J1: 10 | K1: 11 | L1: 12 | M1: 13 | N1: 14 | O1: 15 | P1: 16 | Q1: 17 | R1: 18 | S1: 19 | T1: 20
B2: nroCdpSwf | C2: fecEmision | D2: horEmision | E2: tipCdpSwf | F2: obsGuia | G2: tipDocuEmisorSwf | H2: nroRucEmisorSwf | I2: razonSocialSwf | J2: nroAutorizacionSwf | K2: codEntidadAutorizadoraSwf | L2: tipDocDestinatario | M2: numDocDestinatario | N2: rznSocialDestinatario | O2: tipDocDestinatario | P2: numDocDestinatario | Q2: rznSocialDestinatario | R2: tipDocDestinatario | S2: numDocDestinatario | T2: rznSocialDestinatario
A3: GRR
A6: 1 | B6: 2 | C6: 3 | D6: 4 | E6: 5 | F6: 6 | G6: 7 | H6: 8 | I6: 9 | J6: 10 | K6: 11 | L6: 12 | M6: 13 | N6: 14 | O6: 15 | P6: 16 | Q6: 17 | R6: 18 | S6: 19 | T6: 20 | U6: 21 | V6: 22 | W6: 23
B7: motTrasladoDatosEnvio | C7: desMotivoTrasladoDatosEnvio | D7: psoBrutoTotalBienesDatosEnvio | E7: uniMedidaPesoBrutoDatosEnvio | F7: sustentoDifPesoDatosEnvio | G7: psoBrutoTotalCargaDatosEnvio | H7: uniMedidaPesoBrutoDatosEnvio | I7: numBultosDatosEnvio | J7: numContenedor1 | K7: numPrecinto1 | L7: numContenedor2 | M7: numPrecinto2 | N7: modTrasladoDatosEnvio | O7: fecInicioTrasladoDatosEnvio | P7: fecEntregaTransportistaDatosEnvio | Q7: indTransbordoProgramado | R7: indTrasladoVehCatM1oL | S7: indRetornoVehiculoEnvasesEmbalajes | T7: indRetornoVehiculoVacio | U7: indTrasladoTotalDAMoDS | V7: indRegistroVehiculoConductor | W7: tipEventoDatosEnvio
A8: ENV
A11: 1 | B11: 2 | C11: 3 | D11: 4 | E11: 5 | F11: 6 | G11: 7
B12: tipDocTransportista | C12: numDocTransportista | D12: nomTransportista | E12: numeroRegistroMTCTransportista | F12: numAutorizacionTransportista | G12: codEntidadAutorizadoraTransportista
A13: TTA
A16: 1 | B16: 2 | C16: 3 | D16: 4 | E16: 5 | F16: 6
B17: tipVehiculo | C17: numPlacaVehículoPrincipal | D17: tarjetaUnicaCirculacionElecPrincipal | E17: numAutorizacionPrincipal | F17: codEntidadEmisoraPrincipal
A18: VPS | B18: Principal
A19: VPS | B19: Secundario
A21: 1 | B21: 2 | C21: 3 | D21: 4 | E21: 5 | F21: 6 | G21: 7
B22: tipConductor | C22: tipDocumentoConductor | D22: numDocumentoConductor | E22: nombresConductor | F22: apellidosConductor | G22: numLicenciaConducir
A23: CON | B23: Principal
A24: CON | B24: Secundario
A26: 1 | B26: 2 | C26: 3 | D26: 4 | E26: 5 | F26: 6 | G26: 7 | H26: 8
B27: tipDireccionPunto | C27: ubiPartida | D27: dirPartida | E27: longitudPuntoGeorreferenciaPartida | F27: latitudPuntoGeorreferenciaPartida | G27: rucAsociadoPuntoPartida | H27: codEstablecimientoPuntoPartida
A28: PLL | B28: Partida
A29: PLL | B29: Llegada
A31: 1 | B31: 2 | C31: 3 | D31: 4
B32: codPuertoAeropuerto | C32: tipLocacionCodPuertoAeropuerto | D32: nombrePuertoAeropuerto
A33: EPA
A36: 1 | B36: 2 | C36: 3 | D36: 4 | E36: 5 | F36: 6 | G36: 7 | H36: 8 | I36: 9 | J36: 10 | K36: 11 | L36: 12
B37: lineaBien | C37: canBien | D37: uniMedidaBien | E37: desItem | F37: codItem | G37: codProductoSunatItem | H37: codProductoGTINItem | I37: tipEstructuraGTINItem | J37: nomConceptoItem | K37: codConceptoItem | L37: valueItem
A38: BIE
A41: 1 | B41: 2 | C41: 3 | D41: 4 | E41: 5 | F41: 6
B42: tipDocRel | C42: codTipDocRel | D42: numDocRel | E42: numDocEmisorDoc | F42: tipDocEmisorDocRel
A43: DOR

Sheet GRE-Transportista
B1: GUIA REMISION ELECTRÓNICA TRANSPORTISTA
B2: N° | C2: DATO | D2: NIVEL | E2: CONDICIÓN INFORMÁTICA | F2: TIPO Y LONGITUD | G2: FORMATO | H2: TAG UBL | I2: VALIDACIÓN / CONDICIÓN | J2: TIPO DE RETORNO | K2: CODIGO RETORNO | L2: MENSAJE DE RETORNO | M2: REST o XSL | N2: LISTADOS
B3: - | C3: -
B4: Datos de guía de remisión
B5: 1 | C5: Version del UBL | D5: Global | E5: M | F5: an..3 | G5: 2.1 | H5: /DespatchAdvice/cbc:UBLVersionID | I5: No existe el Tag UBL o es vacío | J5: ERROR | K5: 2111 | L5: =VLOOKUP(K5,[1]CódigosRetorno!$A$2:$B$1996,2,FALSE) -> El XML no contiene el tag o no existe informacion de UBLVersionID | M5: XSL
I6: El valor del Tag UBL es diferente a "2.1" | J6: ERROR | K6: 2110 | L6: =VLOOKUP(K6,[1]CódigosRetorno!$A$2:$B$1996,2,FALSE) -> UBLVersionID - La versión del UBL no es correcta | M6: XSL
B7: 2 | C7: Version de la estructura del documento | D7: Global | E7: M | F7: an..3 | G7: 2.0 | H7: /DespatchAdvice/cbc:CustomizationID | I7: No existe el Tag UBL o es vacío | J7: ERROR | K7: 2113 | L7: =VLOOKUP(K7,[1]CódigosRetorno!$A$2:$B$1996,2,FALSE) -> El XML no contiene el tag o no existe informacion de CustomizationID | M7: XSL
I8: El valor del Tag UBL es diferente a "2.0" | J8: ERROR | K8: 2112 | L8: =VLOOKUP(K8,[1]CódigosRetorno!$A$2:$B$1996,2,FALSE) -> CustomizationID - La version del documento no es correcta | M8: XSL
B9: 3 | C9: Numeracion, conformada por serie y Número correlativo | D9: Global | E9: M | F9: an..13 | G9: V###-NNNNNNNN | H9: /DespatchAdvice/cbc:ID | I9: El formato del Tag UBL es diferente a: [V][A-Z0-9]{3}-[0-9]{1,8} | J9: ERROR | K9: 1001 | L9: =VLOOKUP(K9,[1]CódigosRetorno!$A$2:$B$1996,2,FALSE) -> ID - El dato SERIE-CORRELATIVO no cumple con el formato de acuerdo al tipo de comprobante | M9: XSL
I10: El número de serie del Tag UBL es diferente al número de serie del archivo | J10: ERROR | K10: 1035 | L10: =VLOOKUP(K10,[1]CódigosRetorno!$A$2:$B$1996,2,FALSE) -> Numero de Serie del nombre del archivo no coincide con el consignado en el contenido del archivo XML | M10: XSL
I11: El número de documento del Tag UBL es diferente al número de documento del archivo | J11: ERROR | K11: 1036 | L11: =VLOOKUP(K11,[1]CódigosRetorno!$A$2:$B$1996,2,FALSE) -> Número de documento en el nombre del archivo no coincide con el consignado en el contenido del XML | M11: XSL
I12: El valor del Tag UBL se encuentra en el listado con indicador de estado igual a '1' | J12: ERROR | K12: 1033 | L12: =VLOOKUP(K12,[1]CódigosRetorno!$A$2:$B$1996,2,FALSE) -> El comprobante fue registrado previamente con otros datos | M12: REST | N12: Comprobantes de pagos electrónicos
I13: El valor del Tag UBL se encuentra en el listado con indicador de estado igual a '2' | J13: ERROR | K13: 1032 | L13: =VLOOKUP(K13,[1]CódigosRetorno!$A$2:$B$1996,2,FALSE) -> El comprobante ya esta informado y se encuentra con estado anulado o rechazado | M13: REST | N13: Comprobantes de pagos electrónicos
B14: =+B9+1 -> 4 | C14: Fecha de emisión | D14: Global | E14: M | F14: an10 | G14: YYYY-MM-DD | H14: /DespatchAdvice/cbc:IssueDate | I14: El valor del Tag UBL no cumple con el formato establecido | J14: ERROR | K14: 3436 | L14: =VLOOKUP(K14,[1]CódigosRetorno!$A$2:$B$1996,2,FALSE) -> El campo de fecha de emision no cumple con el formato establecido | M14: XSL
I15: La diferencia entre la fecha de recepción del XML y el valor del Tag UBL es mayor al límite del listado (1 día) | J15: ERROR | K15: 2108 | L15: =VLOOKUP(K15,[1]CódigosRetorno!$A$2:$B$1996,2,FALSE) -> Presentacion fuera de fecha | M15: REST | N15: Parámetros (004)
I16: El valor del Tag UBL es mayor a la fecha de recepción (TODAY) o es 12/07/2022 | J16: ERROR | K16: 2329 | L16: =VLOOKUP(K16,[1]CódigosRetorno!$A$2:$B$1996,2,FALSE) -> La fecha de emision se encuentra fuera del limite permitido | M16: XSL
B17: =+B14+1 -> 5 | C17: Hora de emisión | D17: Global | E17: M | F17: an8 | G17: hh:mm:ss | H17: /DespatchAdvice/cbc:IssueTime | I17: No existe el Tag UBL | J17: ERROR | K17: 3437 | L17: =VLOOKUP(K17,[1]CódigosRetorno!$A$2:$B$1996,2,FALSE) -> No existe informacion en el campo de hora de emision | M17: XSL
I18: El valor del Tag UBL no cumple con el formato establecido | J18: ERROR | K18: 3438 | L18: =VLOOKUP(K18,[1]CódigosRetorno!$A$2:$B$1996,2,FALSE) -> El campo de hora de emision no cumple con el formato establecido | M18: XSL
B19: =+B17+1 -> 6 | C19: Tipo de documento (Guia) | D19: Global | E19: M | F19: an..2 | G19: "31" | H19: /DespatchAdvice/cbc:DespatchAdviceTypeCode | I19: No existe el Tag UBL o es vacío | J19: ERROR | K19: 1050 | L19: =VLOOKUP(K19,[1]CódigosRetorno!$A$2:$B$1996,2,FALSE) -> El XML no contiene informacion en el tag DespatchAdviceTypeCode. | M19: XSL
I20: El valor del Tag UBL es diferente a "31" | J20: ERROR | K20: 1051 | L20: =VLOOKUP(K20,[1]CódigosRetorno!$A$2:$B$1996,2,FALSE) -> DespatchAdviceTypeCode - El valor del tipo de guía es inválido. | M20: XSL
G21: "PE:SUNAT" | H21: @listAgencyName | I21: Si existe el atributo, el valor ingresado es diferente a 'PE:SUNAT' | J21: OBSERV | K21: 4251 | L21: =VLOOKUP(K21,[1]CódigosRetorno!$A$2:$B$1996,2,FALSE) -> El dato ingresado como atributo @listAgencyName es incorrecto. | M21: XSL
G22: "Tipo de Documento" | H22: @listName | I22: Si existe el atributo, el valor ingresado es diferente a 'Tipo de Documento' | J22: OBSERV | K22: 4252 | L22: =VLOOKUP(K22,[1]CódigosRetorno!$A$2:$B$1996,2,FALSE) -> El dato ingresado como atributo @listName es incorrecto. | M22: XSL
G23: "urn:pe:gob:sunat:cpe:see:gem:catalogos:catalogo01" | H23: @listURI | I23: Si existe el atributo, el valor ingresado es diferente a 'urn:pe:gob:sunat:cpe:see:gem:catalogos:catalogo01' | J23: OBSERV | K23: 4253 | L23: =VLOOKUP(K23,[1]CódigosRetorno!$A$2:$B$1996,2,FALSE) -> El dato ingresado como atributo @listURI es incorrecto. | M23: XSL
B24: =+B19+1 -> 7 | C24: Observaciones (Texto) | D24: Global | E24: C | F24: an..250 | H24: /DespatchAdvice/cbc:Note | I24: Si el Tag UBL existe, el formato del Tag UBL es diferente a alfanumérico de hasta 250 caracteres o es vacío (se considera cualquier carácter incluido espacio, no se permite ningún otro "whitespace character": salto de línea, tab, fin de línea, etc. Tampoco se permite solo espacios en blanco) | J24: OBSERV | K24: 4186 | L24: =VLOOKUP(K24,[1]CódigosRetorno!$A$2:$B$1996,2,FALSE) -> cbc:Note - El campo observaciones supera la cantidad maxima especificada (250 carácteres). | M24: XSL
B25: Datos del Transportista
B26: =B24+1 -> 8 | C26: Tipo y número de documento de identidad del transportista | D26: Global | E26: M | F26: an1 | G26: "6" | H26: /DespatchAdvice/cac:DespatchSupplierParty/cac:Party/cac:PartyIdentification/cbc:ID@schemeID | I26: No existe el Tag UBL o es vacío | J26: ERROR | K26: 2678 | L26: =VLOOKUP(K26,[1]CódigosRetorno!$A$2:$B$1996,2,FALSE) -> El XML no contiene el atributo o no existe información del tipo de documento del emisor | M26: XSL
I27: El valor del Tag UBL es diferente a "6" | J27: ERROR | K27: 2511 | L27: =VLOOKUP(K27,[1]CódigosRetorno!$A$2:$B$1996,2,FALSE) -> El tipo de documento no es aceptado. | M27: XSL
G28: "Documento de Identidad" | H28: @schemeName | I28: Si existe el atributo, el valor ingresado es diferente a 'Documento de Identidad' | J28: OBSERV | K28: 4255 | L28: =VLOOKUP(K28,[1]CódigosRetorno!$A$2:$B$1996,2,FALSE) -> El dato ingresado como atributo @schemeName es incorrecto. | M28: XSL
G29: "PE:SUNAT" | H29: @schemeAgencyName | I29: Si existe el atributo, el valor ingresado es diferente a 'PE:SUNAT' | J29: OBSERV | K29: 4256 | L29: =VLOOKUP(K29,[1]CódigosRetorno!$A$2:$B$1996,2,FALSE) -> El dato ingresado como atributo @schemeAgencyName es incorrecto. | M29: XSL
G30: "urn:pe:gob:sunat:cpe:see:gem:catalogos:catalogo06" | H30: @schemeURI | I30: Si existe el atributo, el valor ingresado es diferente a 'urn:pe:gob:sunat:cpe:see:gem:catalogos:catalogo06' | J30: OBSERV | K30: 4257 | L30: =VLOOKUP(K30,[1]CódigosRetorno!$A$2:$B$1996,2,FALSE) -> El dato ingresado como atributo @schemeURI es incorrecto. | M30: XSL
F31: an11 | G31: n11 | H31: /DespatchAdvice/cac:DespatchSupplierParty/cac:Party/cac:PartyIdentification/cbc:ID | I31: El Tag UBL es diferente al RUC del nombre del XML | J31: ERROR | K31: 1034 | L31: =VLOOKUP(K31,[1]CódigosRetorno!$A$2:$B$1996,2,FALSE) -> Número de RUC del nombre del archivo no coincide con el consignado en el contenido del archivo XML | M31: XSL
I32: El valor del Tag UBL tiene un ind_estado diferente "00" en el listado | J32: ERROR | K32: 3349 | L32: =VLOOKUP(K32,[1]CódigosRetorno!$A$2:$B$1996,2,FALSE) -> El RUC del Transportista no esta activo | M32: REST | N32: Contribuyentes
I33: El valor del Tag UBL tiene un ind_condicion diferente a "00" en el listado | J33: ERROR | K33: 3350 | L33: =VLOOKUP(K33,[1]CódigosRetorno!$A$2:$B$1996,2,FALSE) -> El RUC del Transportista no esta habido | M33: REST | N33: Contribuyentes
I34: Se encuentra afecto exclusivamente solo a los tributos Renta de primera categoría, Renta de segunda categoría o Renta de cuarta categoría (no está afecto a ningún otro tributo distinto de los indicados) | J34: ERROR | K34: 3439 | L34: =VLOOKUP(K34,[1]CódigosRetorno!$A$2:$B$1996,2,FALSE) -> El RUC no esta afecto a los tributos autorizados | M34: REST | N34: Afectacion
B35: =B26+1 -> 9 | C35: Apellidos y Nombres o denominacion o razón social del transportista | D35: Global | E35: M | F35: an..250 | H35: /DespatchAdvice/cac:DespatchSupplierParty/cac:Party/cac:PartyLegalEntity/cbc:RegistrationName | I35: No existe el Tag UBL o es vacío | J35: ERROR | K35: 1037 | L35: =VLOOKUP(K35,[1]CódigosRetorno!$A$2:$B$1996,2,FALSE) -> El XML no contiene el tag o no existe informacion de RegistrationName del emisor del documento | M35: XSL
I36: El formato del Tag UBL es diferente a alfanumérico de hasta 250 caracteres (se considera cualquier carácter incluido espacio, no se permite ningún otro "whitespace character": salto de línea, tab, fin de línea, etc. Tampoco se permite solo espacios en blanco) | J36: OBSERV | K36: 4338 | L36: =VLOOKUP(K36,[1]CódigosRetorno!$A$2:$B$1996,2,FALSE) -> RegistrationName - El nombre o razon social del emisor no cumple con el estandar | M36: XSL
B37: =B35+1 -> 10 | C37: Número de Registro MTC | D37: Global | E37: C | F37: an..20 | H37: /DespatchAdvice/cac:Shipment/cac:ShipmentStage/cac:CarrierParty/cac:PartyLegalEntity/cbc:CompanyID | I37: No existe el Tag UBL o es vacío | J37: OBSERV | K37: 4391 | L37: =VLOOKUP(K37,[1]CódigosRetorno!$A$2:$B$1996,2,FALSE) -> El Numero de Registro MTC del transportista no existe o no contiene informacion | M37: XSL
I38: Si el Tag UBL existe y es diferente de vacío, el formato del Tag UBL es diferente a alfanumérico de hasta 20 caracteres (solo se permite letras y números, no se permite ningún otro 'whitespace character': espacio, salto de línea, tab, fin de línea, etc. Tampoco se permite solo espacios en blanco o solamente ceros) | J38: OBSERV | K38: 4392 | L38: =VLOOKUP(K38,[1]CódigosRetorno!$A$2:$B$1996,2,FALSE) -> El Numero de Registro MTC del transportista no cumple con el formato establecido | M38: XSL
I39: Si el Tag UBL existe y es diferente de vacío, el valor del Tag UBL no se encuentra en el listado | J39: OBSERV | K39: 4393 | L39: =VLOOKUP(K39,[1]CódigosRetorno!$A$2:$B$1996,2,FALSE) -> El Numero de Registro MTC del transportista no se encuentra en las bases consultadas | M39: REST | N39: Información de Registro MTC
I40: Si el Tag UBL existe y es diferente de vacío, existe otro cac:PartyLegalEntity | J40: ERROR | K40: 3353 | L40: =VLOOKUP(K40,[1]CódigosRetorno!$A$2:$B$1996,2,FALSE) -> Solo debe consignar un Numero de autorizacion | M40: XSL
B41: 11 | C41: Entidad emisora de la autorización especial - Transportista Número de autorización especial emitido por la entidad - Transportista | D41: Global | E41: C | F41: an..50 | H41: /DespatchAdvice/cac:Shipment/cac:ShipmentStage/cac:CarrierParty/cac:AgentParty/cac:PartyLegalEntity/cbc:CompanyID (Número de autorización) | I41: Si el Tag UBL existe y es diferente de vacío, el formato del Tag UBL es diferente a alfanumérico de 3 a 50 caracteres (se considera cualquier carácter incluido espacio, no se permite ningún otro 'whitespace character': salto de línea, tab, fin de línea, etc. Tampoco se permite solo espacios en blanco) | J41: OBSERV | K41: 4396 | L41: =VLOOKUP(K41,[1]CódigosRetorno!$A$2:$B$1996,2,FALSE) -> El Numero de autorizacion del transportista no cumple con el formato establecido | M41: XSL
I42: Si el Tag UBL existe y es diferente de vacío, existe otro cac:PartyLegalEntity | J42: ERROR | K42: 3353 | L42: =VLOOKUP(K42,[1]CódigosRetorno!$A$2:$B$1996,2,FALSE) -> Solo debe consignar un Numero de autorizacion | M42: XSL
F43: an2 | G43: (Catálogo N° D-37) | H43: /DespatchAdvice/cac:Shipment/cac:ShipmentStage/cac:CarrierParty/cac:AgentParty/cac:PartyLegalEntity/cbc:CompanyID@schemeID (Código de entidad autorizadora) | I43: Si existe 'Número de autorización' con valor diferente de vacío, no existe el atributo o es vacío | J43: OBSERV | K43: 4394 | L43: =VLOOKUP(K43,[1]CódigosRetorno!$A$2:$B$1996,2,FALSE) -> Debe indicar la entidad autorizadora de la autorizacion especial | M43: XSL | N43: Catálogo (D-37)
I44: Si existe el atributo, el valor ingresado no se encuentra en el listado y es diferente de vacío | J44: OBSERV | K44: 4395 | L44: =VLOOKUP(K44,[1]CódigosRetorno!$A$2:$B$1996,2,FALSE) -> El Codigo de entidad autorizadora es invalido | M44: XSL | N44: Catálogo (D-37)
I45: Si existe el atributo y es diferente de vacío, el 'Número de autorización' es vacío | J45: OBSERV | K45: 4397 | L45: =VLOOKUP(K45,[1]CódigosRetorno!$A$2:$B$1996,2,FALSE) -> SI existe el Codigo de entidad autorizadora, debe consignar el Numero de autorizacion especial de la empresa | M45: XSL
G46: "Entidad Autorizadora" | H46: @schemeName | I46: Si existe el atributo, el valor ingresado es diferente a 'Entidad Autorizadora' | J46: OBSERV | K46: 4255 | L46: =VLOOKUP(K46,[1]CódigosRetorno!$A$2:$B$1996,2,FALSE) -> El dato ingresado como atributo @schemeName es incorrecto. | M46: XSL
G47: "PE:SUNAT" | H47: @schemeAgencyName | I47: Si existe el atributo, el valor ingresado es diferente a 'PE:SUNAT' | J47: OBSERV | K47: 4256 | L47: =VLOOKUP(K47,[1]CódigosRetorno!$A$2:$B$1996,2,FALSE) -> El dato ingresado como atributo @schemeAgencyName es incorrecto. | M47: XSL
B48: Documento relacionado - solo se permite un documento, excepto hasta 2 si se ingresa alguno de los códigos "31", "65", "66", "67", "68", "69", o más de 2 si se ingresa código "09" con serie electrónica
B49: =B41+1 -> 12 | C49: Tipo de documento (Descripción) | D49: Global | E49: C | F49: an..120 | H49: /DespatchAdvice/cac:AdditionalDocumentReference/cbc:DocumentType | I49: Si existe 'Código del tipo de documento relacionado' y es diferente de vacío, y no existe el Tag UBL o es vacío | J49: OBSERV | K49: 4371 | L49: =VLOOKUP(K49,[1]CódigosRetorno!$A$2:$B$1996,2,FALSE) -> El XML no contiene el tag o no existe informacion de la descripcion del tipo de documento relacionado | M49: XSL
I50: Si el Tag UBL existe y es diferente de vacío, no existe 'Código del tipo de documento relacionado' o es vacío | J50: OBSERV | K50: 4410 | L50: =VLOOKUP(K50,[1]CódigosRetorno!$A$2:$B$1996,2,FALSE) -> Si existe descripcion del documento relacionado debe existir informacion del codigo y numero del documento relacionado | M50: XSL
I51: El formato es diferente a alfanumérico de hasta 120 caracteres (se considera cualquier carácter incluido espacio, no se permite ningún otro "whitespace character": salto de línea, tab, fin de línea, etc. Tampoco se permite solo espacios en blanco) | J51: OBSERV | K51: 4372 | L51: =VLOOKUP(K51,[1]CódigosRetorno!$A$2:$B$1996,2,FALSE) -> La descripcion del tipo de documento relacionado no cumple con el estandar | M51: XSL
B52: =+B49+1 -> 13 | C52: Código del tipo de documento relacionado | D52: Global | E52: C | F52: an2 | G52: (Catálogo N° 61) | H52: /DespatchAdvice/cac:AdditionalDocumentReference/cbc:DocumentTypeCode | I52: Si el Tag UBL existe y es diferente de vacío, el valor del Tag UBL no está en el listado de acuerdo al tipo de guía | J52: ERROR | K52: 2692 | L52: =VLOOKUP(K52,[1]CódigosRetorno!$A$2:$B$1996,2,FALSE) -> El tipo de documento relacionado no es válido | M52: XSL | N52: Catálogo (061)
I53: Si el Tag UBL existe y es diferente de vacío, el 'Número de documento relacionado' es vacío | J53: ERROR | K53: 3403 | L53: =VLOOKUP(K53,[1]CódigosRetorno!$A$2:$B$1996,2,FALSE) -> El XML no contiene el tag o no existe informacion del numero de documento relacionado | M53: XSL
I54: Si existe un 'Documento relacionado' con 'Código del tipo de documento relacionado' igual a "31", "65", "66", "67", "68", "69", existe más de dos 'Documento relacionado' (cac:AdditionalDocumentReference con cbc:DocumentTypeCode diferente de vacío) | J54: ERROR | K54: 3345 | L54: =VLOOKUP(K54,[1]CódigosRetorno!$A$2:$B$1996,2,FALSE) -> Solo corresponde ingresar hasta dos 2 documentos relacionados si uno de los tipos de documentos relacionados es "31", "65", "66", "67", "68" o "69" | M54: XSL
I55: Si no existe un 'Documento relacionado' con 'Código del tipo de documento relacionado' igual a "31", "65", "66", "67", "68", "69", y no existe un 'Documento relacionado' con 'Código del tipo de documento relacionado' igual a "09" con número de serie que no empieza con número, existe más de un 'Documento relacionado' (cac:AdditionalDocumentReference con cbc:DocumentTypeCode diferente de vacío) | J55: ERROR | K55: 3346 | L55: =VLOOKUP(K55,[1]CódigosRetorno!$A$2:$B$1996,2,FALSE) -> Solo corresponde ingresar mas de 1 documento relacionado si uno de los tipos de documentos relacionados es "31", "65", "66", "67", "68" o "69", o "09" (solo guia electronica) | M55: XSL
G56: "PE:SUNAT" | H56: @listAgencyName | I56: Si existe el atributo, el valor ingresado es diferente a 'PE:SUNAT' | J56: OBSERV | K56: 4251 | L56: =VLOOKUP(K56,[1]CódigosRetorno!$A$2:$B$1996,2,FALSE) -> El dato ingresado como atributo @listAgencyName es incorrecto.
G57: "Documento relacionado al transporte" | H57: @listName | I57: Si existe el atributo, el valor ingresado es diferente a 'Documento relacionado al transporte' | J57: OBSERV | K57: 4252 | L57: =VLOOKUP(K57,[1]CódigosRetorno!$A$2:$B$1996,2,FALSE) -> El dato ingresado como atributo @listName es incorrecto.
G58: "urn:pe:gob:sunat:cpe:see:gem:catalogos:catalogo61" | H58: @listURI | I58: Si existe el atributo, el valor ingresado es diferente a 'urn:pe:gob:sunat:cpe:see:gem:catalogos:catalogo61' | J58: OBSERV | K58: 4253 | L58: =VLOOKUP(K58,[1]CódigosRetorno!$A$2:$B$1996,2,FALSE) -> El dato ingresado como atributo @listURI es incorrecto. | M58: XSL
B59: =B52+1 -> 14 | C59: Número de documento relacionado | D59: Global | E59: C | F59: an..100 | H59: /DespatchAdvice/cac:AdditionalDocumentReference/cbc:ID | I59: Si el valor del Tag UBL es diferente de vacío, el 'Código del tipo de documento relacionado' concatenado con el valor del Tag UBL se repite en el /DespatchAdvice | J59: ERROR | K59: 3340 | L59: =VLOOKUP(K59,[1]CódigosRetorno!$A$2:$B$1996,2,FALSE) -> El documento relacionado al traslado de mercancias se encuentra duplicado | M59: XSL
I60: Si el valor del Tag UBL es diferente de vacío, el 'Código del tipo de documento relacionado' no existe o es vacío | J60: ERROR | K60: 3376 | L60: =VLOOKUP(K60,[1]CódigosRetorno!$A$2:$B$1996,2,FALSE) -> El XML no contiene el tag o no existe informacion del Codigo de tipo de documento relacionado | M60: XSL
I61: Si el 'Código del tipo de documento relacionado' es '01', el formato del Tag UBL es diferente a <Serie>-<Numero> con la siguiente estructura: - [F][A-Z0-9]{3}-[0-9]{1,8} - (E001)-[0-9]{1,8} - [0-9]{1,4}-[0-9]{1,8} El campo <Numero> debe ser mayor a cero | J61: ERROR | K61: 3441 | L61: =VLOOKUP(K61,[1]CódigosRetorno!$A$2:$B$1996,2,FALSE) -> El numero de documento relacionado al traslado de mercancias no cumple con el formato establecido | M61: XSL
I62: Si el 'Código del tipo de documento relacionado' es '03', el formato del Tag UBL es diferente a <Serie>-<Numero> con la siguiente estructura: - [B][A-Z0-9]{3}-[0-9]{1,8} - (EB01)-[0-9]{1,8} - [0-9]{1,4}-[0-9]{1,8} El campo <Numero> debe ser mayor a cero | J62: ERROR | K62: 3441 | L62: =VLOOKUP(K62,[1]CódigosRetorno!$A$2:$B$1996,2,FALSE) -> El numero de documento relacionado al traslado de mercancias no cumple con el formato establecido | M62: XSL
I63: Si el 'Código del tipo de documento relacionado' es '04', el formato del Tag UBL es diferente a <Serie>-<Numero> con la siguiente estructura: - [L][A-Z0-9]{3}-[0-9]{1,8} - (E001)-[0-9]{1,8} - [0-9]{1,4}-[0-9]{1,8} El campo <Numero> debe ser mayor a cero | J63: ERROR | K63: 3441 | L63: =VLOOKUP(K63,[1]CódigosRetorno!$A$2:$B$1996,2,FALSE) -> El numero de documento relacionado al traslado de mercancias no cumple con el formato establecido | M63: XSL
I64: Si el 'Código del tipo de documento relacionado' es '50' o '52', el formato del Tag UBL es diferente de: - [0-9]{3}-[0-9]{4}-[0-9]{2}-[0-9]{1,6} donde: [0-9]{3}: Código de la Aduana, [0-9]{4}: Año, [0-9]{2} Régimen aduanero, [0-9]{1,6} Correlativo | J64: ERROR | K64: 3441 | L64: =VLOOKUP(K64,[1]CódigosRetorno!$A$2:$B$1996,2,FALSE) -> El numero de documento relacionado al traslado de mercancias no cumple con el formato establecido | M64: XSL
I65: Si el 'Código del tipo de documento relacionado' es '80', el formato del Tag UBL es diferente a numérico hasta 15 dígitos (debe ser mayor a cero) | J65: ERROR | K65: 3441 | L65: =VLOOKUP(K65,[1]CódigosRetorno!$A$2:$B$1996,2,FALSE) -> El numero de documento relacionado al traslado de mercancias no cumple con el formato establecido | M65: XSL
I66: Si el 'Código del tipo de documento relacionado' es '12', el formato del Tag UBL es diferente a <Serie>-<Numero> con la siguiente estructura: - [a-zA-Z0-9-]{1,20}-[a-zA-Z0-9-]{1,20} | J66: ERROR | K66: 3441 | L66: =VLOOKUP(K66,[1]CódigosRetorno!$A$2:$B$1996,2,FALSE) -> El numero de documento relacionado al traslado de mercancias no cumple con el formato establecido | M66: XSL
I67: Si el 'Código del tipo de documento relacionado' es '48', el formato del Tag UBL es diferente a <Serie>-<Numero> con la siguiente estructura: - [0-9]{1,4}-[0-9]{1,7} El campo <Numero> debe ser mayor a cero | J67: ERROR | K67: 3441 | L67: =VLOOKUP(K67,[1]CódigosRetorno!$A$2:$B$1996,2,FALSE) -> El numero de documento relacionado al traslado de mercancias no cumple con el formato establecido | M67: XSL
I68: Si el 'Código del tipo de documento relacionado' es '09', el formato del Tag UBL es diferente a <Serie>-<Numero> con la siguiente estructura: - [T][A-Z0-9]{3}-[0-9]{1,8} - (EG07)-[0-9]{1,8} - (EG02)-[0-9]{1,8} - [0-9]{1,4}-[0-9]{1,8} El campo <Numero> debe ser mayor a cero | J68: ERROR | K68: 3441 | L68: =VLOOKUP(K68,[1]CódigosRetorno!$A$2:$B$1996,2,FALSE) -> El numero de documento relacionado al traslado de mercancias no cumple con el formato establecido | M68: XSL
I69: Si el 'Código del tipo de documento relacionado' es '31', el formato del Tag UBL es diferente a <Serie>-<Numero> con la siguiente estructura: - [V][A-Z0-9]{3}-[0-9]{1,8} - (EG03)-[0-9]{1,8} - (EG04)-[0-9]{1,8} El campo <Numero> debe ser mayor a cero | J69: ERROR | K69: 3441 | L69: =VLOOKUP(K69,[1]CódigosRetorno!$A$2:$B$1996,2,FALSE) -> El numero de documento relacionado al traslado de mercancias no cumple con el formato establecido | M69: XSL
I70: Si el 'Código del tipo de documento relacionado' es '82', '65', '66', '67', '68' o '69', el formato del Tag UBL es diferente a alfanumérico de hasta 100 caracteres (se considera cualquier carácter, no permite 'whitespace character': espacio, salto de línea, fin de línea, tab, etc.) | J70: ERROR | K70: 3441 | L70: =VLOOKUP(K70,[1]CódigosRetorno!$A$2:$B$1996,2,FALSE) -> El numero de documento relacionado al traslado de mercancias no cumple con el formato establecido | M70: XSL
I71: Si el 'Código de tipo de documento' es '50' o '52', el valor del Tag UBL no se encuentra en el listado | J71: ERROR | K71: 3341 | L71: =VLOOKUP(K71,[1]CódigosRetorno!$A$2:$B$1996,2,FALSE) -> No existe el numero de Declaracion Aduanera de Mercancias (DAM) o el Declaracion Simplificada (DS) | M71: REST | N71: Detalle Guia Remisión Electrónica
I72: Si el 'Código de tipo de documento' es '31', el valor del Tag UBL no se encuentra en el listado con estado de "Baja - por cambio de destinatario" | J72: ERROR | K72: 2536 | L72: =VLOOKUP(K72,[1]CódigosRetorno!$A$2:$B$1996,2,FALSE) -> La serie y numero de la GRE consignada como documento relacionado no se encuentra registrado con baja por cambio de destinatario | M72: REST | N72: Número de DAM y DS
I73: Si el 'Código de tipo de documento' es '80' y se encuentra referenciada en otras GRE - remitente o GRE - transportista según el listado en los últimos 15 días calendario contados a partir de la fecha de recepción de la GRE | J73: ERROR | K73: 3342 | L73: =VLOOKUP(K73,[1]CódigosRetorno!$A$2:$B$1996,2,FALSE) -> La Constancia de Deposito ingresada ya ha sido referenciada en otra GRE emitida | M73: REST | N73: Detalle Guia Remisión Electrónica
I74: Si existe el Tag UBL y el código de tipo de documento es '80', el valor del Tag UBL no se encuentra en el listado en los últimos 15 días calendario contados a partir de la fecha de recepción de la GRE | J74: OBSERV | K74: 4404 | L74: =VLOOKUP(K74,[1]CódigosRetorno!$A$2:$B$1996,2,FALSE) -> La SUNAT no cuenta con la informacion en los ultimos 15 dias de la Constancia de Deposito en sus sistemas | M74: REST | N74: Constancias de depósito Detracciones / IVAP
I75: Si el 'Código de tipo de documento' es '09' y la serie no empieza con número, el valor del Tag UBL no se encuentra en el listado para el emisor de documento | J75: ERROR | K75: 3433 | L75: =VLOOKUP(K75,[1]CódigosRetorno!$A$2:$B$1996,2,FALSE) -> La GRE remitente no existe | M75: REST | N75: Comprobantes de pagos electrónicos
I76: Si el 'Código de tipo de documento' es '01', '03' o '04' y la serie no empieza con número, el valor del Tag UBL no se encuentra en el listado para el emisor de documento | J76: OBSERV | K76: 4382 | L76: =VLOOKUP(K76,[1]CódigosRetorno!$A$2:$B$1996,2,FALSE) -> El numero de comprobante consignado como documento relacionado no existe | M76: REST | N76: Comprobantes de pagos electrónicos
I77: Si el 'Código de tipo de documento' es '01', '03', '04', '09' o '48' y la serie empieza con número, el valor del Tag UBL no se encuentra en el listado para el emisor de documento | J77: ERROR | K77: 3207 | L77: =VLOOKUP(K77,[1]CódigosRetorno!$A$2:$B$1996,2,FALSE) -> Comprobante físico no se encuentra autorizado | M77: REST | N77: Autorizaciones de comprobantes físicos
B78: =B59+1 -> 15 | C78: Número de RUC del emisor del documento relacionado | D78: Global | E78: C | F78: an11 | G78: n11 | H78: /DespatchAdvice/cac:AdditionalDocumentReference/cac:IssuerParty/cac:PartyIdentification/cbc:ID (Número de RUC del emisor del documento) | I78: Si el 'Código del tipo de documento relacionado' es '01', '03', '04', '12', '48', '09', '31' no existe el Tag UBL o es vacío | J78: ERROR | K78: 3380 | L78: =VLOOKUP(K78,[1]CódigosRetorno!$A$2:$B$1996,2,FALSE) -> Debe consignar el RUC del emisor del documento relacionado | M78: XSL
I79: Si el Tag UBL existe y es diferente de vacío y el 'Código del tipo de documento relacionado' es '09', y la serie no empieza con número, el valor del Tag UBL es diferente al RUC del remitente | J79: ERROR | K79: 3381 | L79: =VLOOKUP(K79,[1]CódigosRetorno!$A$2:$B$1996,2,FALSE) -> El RUC del emisor del documento relacionado no corresponde | M79: XSL
I80: Si el Tag UBL existe y es diferente de vacío y el 'Código del tipo de documento relacionado' es '31', y la serie no empieza con número, el valor del Tag UBL es diferente al RUC del transportista | J80: ERROR | K80: 3381 | L80: =VLOOKUP(K80,[1]CódigosRetorno!$A$2:$B$1996,2,FALSE) -> El RUC del emisor del documento relacionado no corresponde | M80: XSL
I81: Si el Tag UBL existe y es diferente de vacío, el valor del Tag UBL no existe en el listado | J81: ERROR | K81: 3408 | L81: =VLOOKUP(K81,[1]CódigosRetorno!$A$2:$B$1996,2,FALSE) -> El Numero de RUC del emisor del documento relacionado no existe | M81: REST | N81: Contribuyentes
F82: an1 | G82: "6" | H82: /DespatchAdvice/cac:AdditionalDocumentReference/cac:IssuerParty/cac:PartyIdentification/cbc:ID@schemeID (Tipo de documento de identidad del emisor del documento relacionado) | I82: Si el 'Código del tipo de documento relacionado' es '01', '03', '04', '12', '48', '09', '31', el atributo del atributo no existe o es diferente a 6 (RUC) | J82: ERROR | K82: 3382 | L82: =VLOOKUP(K82,[1]CódigosRetorno!$A$2:$B$1996,2,FALSE) -> El Tipo de documento del emisor del documento relacionado debe ser Numero de RUC | M82: XSL
G83: "Documento de Identidad" | H83: @schemeName | I83: Si existe el atributo, el valor ingresado es diferente a 'Documento de Identidad' | J83: OBSERV | K83: 4255 | L83: =VLOOKUP(K83,[1]CódigosRetorno!$A$2:$B$1996,2,FALSE) -> El dato ingresado como atributo @schemeName es incorrecto. | M83: XSL
G84: "PE:SUNAT" | H84: @schemeAgencyName | I84: Si existe el atributo, el valor ingresado es diferente a 'PE:SUNAT' | J84: OBSERV | K84: 4256 | L84: =VLOOKUP(K84,[1]CódigosRetorno!$A$2:$B$1996,2,FALSE) -> El dato ingresado como atributo @schemeAgencyName es incorrecto. | M84: XSL
G85: "urn:pe:gob:sunat:cpe:see:gem:catalogos: catalogo06" | H85: @schemeURI | I85: Si existe el atributo, el valor ingresado es diferente a 'urn:pe:gob:sunat:cpe:see:gem:catalogos:catalogo06' | J85: OBSERV | K85: 4257 | L85: =VLOOKUP(K85,[1]CódigosRetorno!$A$2:$B$1996,2,FALSE) -> El dato ingresado como atributo @schemeURI es incorrecto. | M85: XSL
B86: Datos del Remitente
B87: =B78+1 -> 16 | C87: Tipo y número de documento de identidad del remitente | D87: Global | E87: M | F87: an1 | G87: (Catálogo N° 06) | H87: /DespatchAdvice/cac:Shipment/cac:Delivery/cac:Despatch/cac:DespatchParty/cac:PartyIdentification/cbc:ID@schemeID (Tipo de documento de identidad) | I87: No existe el atributo o es vacío | J87: ERROR | K87: 2541 | L87: =VLOOKUP(K87,[1]CódigosRetorno!$A$2:$B$1996,2,FALSE) -> El XML no contiene el tag o no existe informacion del tipo de documento identidad del remitente. | M87: XSL | N87: -
I88: El valor del atributo no está en el listado | J88: ERROR | K88: 2542 | L88: =VLOOKUP(K88,[1]CódigosRetorno!$A$2:$B$1996,2,FALSE) -> cac:DespatchSupplierParty/cbc:CustomerAssignedAccountID@schemeID - El valor ingresado como tipo de documento identidad del remitente es incorrecta. | M88: XSL | N88: Catálogo (006)
G89: "Documento de Identidad" | H89: @schemeName | I89: Si existe el atributo, el valor ingresado es diferente a 'Documento de Identidad' | J89: OBSERV | K89: 4255 | L89: =VLOOKUP(K89,[1]CódigosRetorno!$A$2:$B$1996,2,FALSE) -> El dato ingresado como atributo @schemeName es incorrecto. | M89: XSL
G90: "PE:SUNAT" | H90: @schemeAgencyName | I90: Si existe el atributo, el valor ingresado es diferente a 'PE:SUNAT' | J90: OBSERV | K90: 4256 | L90: =VLOOKUP(K90,[1]CódigosRetorno!$A$2:$B$1996,2,FALSE) -> El dato ingresado como atributo @schemeAgencyName es incorrecto. | M90: XSL
G91: "urn:pe:gob:sunat:cpe:see:gem:catalogos:catalogo06" | H91: @schemeURI | I91: Si existe el atributo, el valor ingresado es diferente a 'urn:pe:gob:sunat:cpe:see:gem:catalogos:catalogo06' | J91: OBSERV | K91: 4257 | L91: =VLOOKUP(K91,[1]CódigosRetorno!$A$2:$B$1996,2,FALSE) -> El dato ingresado como atributo @schemeURI es incorrecto. | M91: XSL
F92: an..15 | H92: /DespatchAdvice/cac:Shipment/cac:Delivery/cac:Despatch/cac:DespatchParty/cac:PartyIdentification/cbc:ID (Número de documento de identidad) | I92: No existe el Tag UBL o es vacío | J92: ERROR | K92: 3383 | L92: =VLOOKUP(K92,[1]CódigosRetorno!$A$2:$B$1996,2,FALSE) -> Debe consignar el Numero de documento de identidad del Remitente | M92: XSL
I93: Si el tipo y número de documento de identidad del tranportista es el mismo que el remitente | J93: ERROR | K93: 2560 | L93: =VLOOKUP(K93,[1]CódigosRetorno!$A$2:$B$1996,2,FALSE) -> Transportista no debe ser igual al remitente | M93: XSL
I94: Si "Tipo de documento de identidad del remitente" es "6" y el formato del Tag UBL es diferente a numérico de 11 dígitos | J94: ERROR | K94: 3384 | L94: =VLOOKUP(K94,[1]CódigosRetorno!$A$2:$B$1996,2,FALSE) -> El Numero de documento de identidad del Remitente no cumple con el formato establecido | M94: XSL
I95: Si "Tipo de documento de identidad del remitente" es "6", el valor del Tag UBL no se encuentra en el listado | J95: ERROR | K95: 3385 | L95: =VLOOKUP(K95,[1]CódigosRetorno!$A$2:$B$1996,2,FALSE) -> El Numero de RUC del Remitente no existe | M95: REST | N95: Contribuyentes
I96: Si 'Tipo de documento de identidad del remitente' es "6" (RUC), el valor del Tag UBL tiene un ind_estado diferente "00" en el listado | J96: OBSERV | K96: 4420 | L96: =VLOOKUP(K96,[1]CódigosRetorno!$A$2:$B$1996,2,FALSE) -> El Numero de RUC del Remitente no esta activo | M96: REST | N96: Contribuyentes
I97: Si 'Tipo de documento de identidad del remitente' es "6" (RUC), el valor del Tag UBL tiene un ind_condicion diferente a "00" en el listado | J97: OBSERV | K97: 4421 | L97: =VLOOKUP(K97,[1]CódigosRetorno!$A$2:$B$1996,2,FALSE) -> El Numero de RUC del Remitente no esta habido | M97: REST | N97: Contribuyentes
I98: Si 'Tipo de documento de identidad del destinatario' es '1' y el fomato del Tag UBL es diferente a numérico de 8 dígitos | J98: ERROR | K98: 3384 | L98: =VLOOKUP(K98,[1]CódigosRetorno!$A$2:$B$1996,2,FALSE) -> El Numero de documento de identidad del Remitente no cumple con el formato establecido | M98: XSL
I99: Si 'Tipo de documento de identidad del remitente' es '1', el valor del Tag UBL no se encuentra en base RENIEC | J99: ERROR | K99: 3386 | L99: =VLOOKUP(K99,[1]CódigosRetorno!$A$2:$B$1996,2,FALSE) -> El Numero de DNI del Remitente no existe | M99: REST | N99: Padrón RENIEC
I100: Si 'Tipo de documento de identidad del remitente' es diferente a '1' y diferente de '6', el formato del Tag UBL es diferente a alfanumérico de hasta 15 caracteres (se considera cualquier carácter, no permite 'whitespace character': espacio, salto de línea, fin de línea, tab, etc.) | J100: ERROR | K100: 3384 | L100: =VLOOKUP(K100,[1]CódigosRetorno!$A$2:$B$1996,2,FALSE) -> El Numero de documento de identidad del Remitente no cumple con el formato establecido | M100: XSL
...

Sheet TXT-JSON-GRE-Transportista
B2: GUIA REMISION TRANSPORTISTA
B3: Archivo texto: RRRRRRRRRRR-31-VXXX-99999999.TXT
B4: JSON: GRT
B5: Archivo Texto Orden | C5: Archivo JSON - Atributo | D5: DATO | E5: CONDICIÓN INFORMÁTICA | F5: TIPO Y LONGITUD | G5: FORMATO | H5: TAG UBL
B6: Archivo: Cabecera (RRRRRRRRRRR-31-VXXX-999999999.GRT)
B7: Datos de cabecera
B8: 1 | D8: Primera columna de la fila TXT | E8: M | F8: an3 | G8: GRT
B9: 2 | C9: nroCdpSwf | D9: Numeracion, conformada por serie y Número correlativo | E9: M | F9: an..13 | G9: T###-NNNNNNNN | H9: /DespatchAdvice/cbc:ID
B10: 3 | C10: fecEmision | D10: Fecha de emisión | E10: M | F10: an..10 | G10: YYYY-MM-DD | H10: /DespatchAdvice/cbc:IssueDate
B11: 4 | C11: horEmision | D11: Hora de Emisión | E11: M | F11: an8 | G11: HH:MM:SS | H11: /DespatchAdvice/cbc:IssueTime
B12: 5 | C12: tipCdpSwf | D12: Tipo de documento (Guia) | E12: M | F12: an2 | G12: "31" | H12: /DespatchAdvice/cbc:DespatchAdviceTypeCode
B13: 6 | C13: obsGuia | D13: Observaciones (Texto) | E13: C | F13: an..250 | H13: /DespatchAdvice/cbc:Note
B14: Datos del Remitente
B15: 7 | C15: tipDocuRemitenteSwf | D15: Tipo de documento de identidad del remitente | E15: M | F15: an1 | G15: "6" | H15: /DespatchAdvice/cac:DespatchSupplierParty/cac:Party/cac:PartyIdentification/cbc:ID@schemeID
B16: 8 | C16: nroRuc RemitenteSwf | D16: Número de documento de identidad del remitente | E16: M | F16: an11 | G16: n11 | H16: /DespatchAdvice/cac:DespatchSupplierParty/cac:Party/cac:PartyIdentification/cbc:ID
B17: 9 | C17: razonSocialRemitenteSwf | D17: Apellidos y nombres, denominación o razón social del remitente | E17: M | F17: an..250 | H17: /DespatchAdvice/cac:DespatchSupplierParty/cac:Party/cac:PartyLegalEntity/cbc:RegistrationName
B18: Datos del Destinatario
B19: 10 | C19: tipDocDestinatario | D19: Tipo de documento de identidad del destinatario | E19: M | F19: an1 | G19: (Catálogo N° 06) | H19: /DespatchAdvice/cac:DeliveryCustomerParty/cac:Party/cac:PartyIdentification/cbc:ID@schemeID
B20: 11 | C20: numDocDestinatario | D20: Número de documento de identidad del destinatario | E20: M | F20: an..15 | H20: /DespatchAdvice/cac:DeliveryCustomerParty/cac:Party/cac:PartyIdentification/cbc:ID
B21: 12 | C21: rznSocialDestinatario | D21: Apellidos y nombres, denominación o razón social del destinatario | E21: M | F21: an..250 | H21: /DespatchAdvice/cac:DeliveryCustomerParty/cac:Party/cac:PartyLegalEntity/cbc:RegistrationName
B22: Datos de empresa que subcontrata
B23: 13 | C23: tipDocSubcontratador | D23: Tipo de documento de identidad del subcontratador | E23: C | F23: an1 | G23: "6" | H23: /DespatchAdvice/cac:Shipment/cac:Consignment/cac:LogisticsOperatorParty/cac:PartyIdentification/cbc:ID@schemeID
B24: 14 | C24: numDocSubcontratador | D24: Número de documento de identidad del subcontratador (Número de RUC) | E24: C | F24: an11 | H24: /DespatchAdvice/cac:Shipment/cac:Consignment/cac:LogisticsOperatorParty/cac:PartyIdentification/cbc:ID
B25: 15 | C25: rznSocialSubcontratador | D25: Apellidos y nombres, denominacion o razón social del subcontratador | E25: C | F25: an..250 | H25: /DespatchAdvice/cac:Shipment/cac:Consignment/cac:LogisticsOperatorParty/cac:PartyLegalEntity/cbc:RegistrationName
B26: Datos quien paga el servicio de transporte - solo se completa cuando paga un tercero
B27: 16 | C27: tipDocPagaServicio | D27: Tipo de documento de identidad de quien paga el servicio | E27: C | F27: an1 | G27: (Catálogo N° 06) | H27: /DespatchAdvice/cac:OriginatorCustomerParty/cac:Party/cac:PartyIdentification/cbc:ID@schemeID
B28: 17 | C28: numDocPagaServicio | D28: Número de documento de identidad de quien paga el servicio | E28: C | F28: an..15 | H28: /DespatchAdvice/cac:OriginatorCustomerParty/cac:Party/cac:PartyIdentification/cbc:ID
B29: 18 | C29: rznSocialPagaServicio | D29: Apellidos y nombres, denominacion o razón social de quien paga el servicio | E29: C | F29: an..250 | H29: /DespatchAdvice/cac:OriginatorCustomerParty/cac:Party/cac:PartyLegalEntity/cbc:RegistrationName
B31: Archivo: Detalle (RRRRRRRRRRR-31-VXXX-999999999.TSL)
B32: Datos del traslado
B33: 1 | D33: Primera columna de la fila TXT | E33: M | F33: an3 | G33: TSL
B34: 2 | C34: fecInicioTraslado | D34: Fecha Inicio de traslado | E34: M | F34: an..10 | G34: YYYY-MM-DD | H34: /DespatchAdvice/cac:Shipment/cac:ShipmentStage/cac:TransitPeriod/cbc:StartDate
B35: 3 | C35: anotacionOpcionalBienesTraslado | D35: Anotación opcional sobre los bienes a transportar | E35: C | F35: an..500 | H35: /DespatchAdvice/cac:DespatchLine/cac:Item/cbc:Description
B36: 4 | C36: psoBrutoTotalCargaTraslado | D36: Peso bruto total de la carga | E36: M | F36: an..16 | G36: n(12,3) | H36: /DespatchAdvice/cac:Shipment/cbc:GrossWeightMeasure
B37: 5 | C37: uniMedidaPesoBrutoTraslado | D37: Unidad de medida del peso bruto | E37: M | F37: an3 | G37: "KGM" Kilogramos "TNE" Toneladass | H37: /DespatchAdvice/cac:Shipment/cbc:GrossWeightMeasure@unitCode
B38: 6 | C38: indTrasladoTotalBienes | D38: Indicador de traslado total de bienes | E38: C | F38: an…50 | G38: "SUNAT_Envio_IndicadorTrasladoTotal" | H38: /DespatchAdvice/cac:Shipment/cbc:SpecialInstructions
B39: 7 | C39: indRetornoVehiculoEnvasesEmbalajes | D39: Indicador de retorno de vehículo con envases o embalajes vacíos | E39: C | F39: an…50 | G39: "SUNAT_Envio_IndicadorRetornoVehiculoEnvaseVacio" | H39: /DespatchAdvice/cac:Shipment/cbc:SpecialInstructions
B40: 8 | C40: indRetornoVehiculoVacio | D40: Indicador de retorno de vehículo vacío | E40: C | F40: an…50 | G40: "SUNAT_Envio_IndicadorRetornoVehiculoVacio" | H40: /DespatchAdvice/cac:Shipment/cbc:SpecialInstructions
B41: 9 | C41: indTransbordoProgramado | D41: Indicador de Transbordo Programado | E41: C | F41: an…50 | G41: "SUNAT_Envio_IndicadorTransbordoProgramado" | H41: /DespatchAdvice/cac:Shipment/cbc:SpecialInstructions
B42: 10 | C42: indTransporteSubcontratado | D42: Indicador de transporte subcontratado | E42: C | F42: an…50 | G42: "SUNAT_Envio_IndicadorTrasporteSubcontratado" | H42: /DespatchAdvice/cac:Shipment/cbc:SpecialInstructions
B43: 11 | C43: indPagadorFlete | D43: Indicador de pagador de flete | E43: C | F43: an…50 | G43: "SUNAT_Envio_IndicadorPagadorFlete_Remitente" "SUNAT_Envio_IndicadorPagadorFlete_Subcontratador" "SUNAT_Envio_IndicadorPagadorFlete_Tercero" | H43: /DespatchAdvice/cac:Shipment/cbc:SpecialInstructions
B44: 12 | C44: tipEventoTraslado | D44: Tipo de evento | E44: C | F44: an1 | G44: 1-Transbordo no programado 2-Imposibilidad arribo 3-Imposibilidad entrega | H44: /DespatchAdvice/cac:Shipment/cac:ShipmentStage/cac:TransportEvent/cbc:TransportEventTypeCode
B46: Archivo: Detalle (RRRRRRRRRRR-31-VXXX-999999999.TTA)
B47: Datos del Transportista
B48: 1 | D48: Primera columna de la fila TXT | E48: M | F48: an3 | G48: TTA
B49: 2 | C49: tipDocTransportista | D49: Tipo de documento de identidad | E49: C | F49: an1 | G49: "6" | H49: /DespatchAdvice/cac:Shipment/cac:ShipmentStage/cac:CarrierParty/cac:PartyIdentification/cbc:ID@schemeID
B50: 3 | C50: numDocTransportista | D50: Número de RUC | E50: C | F50: an11 | G50: n11 | H50: /DespatchAdvice/cac:Shipment/cac:ShipmentStage/cac:CarrierParty/cac:PartyIdentification/cbc:ID
B51: 4 | C51: nomTransportista | D51: Apellidos y Nombres o denominación o razón social del transportista | E51: C | F51: an..250 | H51: /DespatchAdvice/cac:Shipment/cac:ShipmentStage/cac:CarrierParty/cac:PartyLegalEntity/cbc:RegistrationName
B52: 5 | C52: numeroRegistroMTCTransportista | D52: Número de Registro MTC | E52: C | F52: an..20 | H52: /DespatchAdvice/cac:Shipment/cac:ShipmentStage/cac:CarrierParty/cac:PartyLegalEntity/cbc:CompanyID
B53: 6 | C53: numAutorizacionTransportista | D53: Entidad emisora de la autorización especial - transportista Número de autorización especial emitido por la entidad - transportista (Número de autorización) | E53: C | F53: an..50 | H53: /DespatchAdvice/cac:Shipment/cac:ShipmentStage/cac:CarrierParty/cac:AgentParty/cac:PartyLegalEntity/cbc:CompanyID
B54: 7 | C54: codEntidadAutorizadoraTransportista | D54: Entidad emisora de la autorización especial - transportista Número de autorización especial emitido por la entidad - transportista (Código de entidad autorizadora) | E54: C | F54: an2 | G54: (Catálogo N.° D-37) | H54: /DespatchAdvice/cac:Shipment/cac:ShipmentStage/cac:CarrierParty/cac:AgentParty/cac:PartyLegalEntity/cbc:CompanyID@schemeID
B56: Archivo: Detalle (RRRRRRRRRRR-31-VXXX-999999999.VPS)
B57: Vehiculo Principal | H57: Principal | I57: Secundario
B58: Vehiculos Secundarios Incremental hasta 2
B59: 1 | D59: Primera columna de la fila TXT | E59: M | F59: an3 | G59: VPS
B60: 2 | C60: tipVehiculo | D60: Tipo de vehiculo: Principal / Secundario | G60: Principal Secundario
B61: 3 | C61: numPlacaVehículoPrincipal | D61: Número de placa del vehículo | E61: C | F61: an..8 | H61: /DespatchAdvice/cac:Shipment/cac:TransportHandlingUnit/cac:TransportEquipment/cbc:ID | I61: /DespatchAdvice/cac:Shipment/cac:TransportHandlingUnit/cac:TransportEquipment/cac:AttachedTransportEquipment/cbc:ID
B62: 4 | C62: tarjetaUnicaCirculacionElecPrincipal | D62: Tarjeta Única de Circulación Electrónica o Certificado de Habilitación vehicular | E62: C | F62: an..15 | H62: /DespatchAdvice/cac:Shipment/cac:TransportHandlingUnit/cac:TransportEquipment/cac:ApplicableTransportMeans/cbc:RegistrationNationalityID | I62: /DespatchAdvice/cac:Shipment/cac:TransportHandlingUnit/cac:TransportEquipment/cac:AttachedTransportEquipment/cac:ApplicableTransportMeans/cbc:RegistrationNationalityID
B63: 5 | C63: numAutorizacionPrincipal | D63: Entidad emisora de la autorización especial - vehículo principal Número de autorización especial del vehículo emitido por la entidad - vehículo principal (Número de autorización) | E63: C | F63: an..50 | H63: /DespatchAdvice/cac:Shipment/cac:TransportHandlingUnit/cac:TransportEquipment/cac:ShipmentDocumentReference/cbc:ID | I63: /DespatchAdvice/cac:Shipment/cac:TransportHandlingUnit/cac:TransportEquipment/cac:AttachedTransportEquipment/cac:ShipmentDocumentReference/cbc:ID
B64: 6 | C64: codEntidadEmisoraPrincipal | D64: Entidad emisora de la autorización especial - vehículo principal Número de autorización especial del vehículo emitido por la entidad - vehículo principal (Código de entidad emisora) | E64: C | F64: an2 | G64: (Catálogo N.° D-37) | H64: /DespatchAdvice/cac:Shipment/cac:TransportHandlingUnit/cac:TransportEquipment/cac:ShipmentDocumentReference/cbc:ID@schemeID | I64: /DespatchAdvice/cac:Shipment/cac:TransportHandlingUnit/cac:TransportEquipment/cac:AttachedTransportEquipment/cac:ShipmentDocumentReference/cbc:ID@schemeID
B66: Archivo: Detalle (RRRRRRRRRRR-31-VXXX-999999999.CON)
B67: Conductor principal
B68: Conductores secundarios - Incremental hasta 2 | H68: Principal | I68: Secundario
B69: 1 | D69: Primera columna de la fila TXT | E69: M | F69: an3 | G69: CON
B70: 2 | C70: tipConductor | D70: Tipo de Conductor | E70: C | F70: an9 | G70: Principal Secundario | H70: /DespatchAdvice/cac:Shipment/cac:ShipmentStage/cac:DriverPerson/cbc:JobTitle | I70: /DespatchAdvice/cac:Shipment/cac:ShipmentStage/cac:DriverPerson/cbc:JobTitle
B71: 3 | C71: tipDocumentoConductor | D71: Tipo de documento de identidad del conductor | E71: C | F71: an1 | G71: (Catálogo N° 06) | H71: /DespatchAdvice/cac:Shipment/cac:ShipmentStage/cac:DriverPerson/cbc:ID@schemeID | I71: /DespatchAdvice/cac:Shipment/cac:ShipmentStage/cac:DriverPerson/cbc:ID@schemeID
B72: 4 | C72: numDocumentoConductor | D72: Número de documento de identidad del conductor | E72: C | F72: an..15 | H72: /DespatchAdvice/cac:Shipment/cac:ShipmentStage/cac:DriverPerson/cbc:ID | I72: /DespatchAdvice/cac:Shipment/cac:ShipmentStage/cac:DriverPerson/cbc:ID
B73: 5 | C73: nombresConductor | D73: Apellidos y nombres del conductor (Nombres) | E73: C | F73: an..250 | H73: /DespatchAdvice/cac:Shipment/cac:ShipmentStage/cac:DriverPerson/cbc:FirstName | I73: /DespatchAdvice/cac:Shipment/cac:ShipmentStage/cac:DriverPerson/cbc:FirstName
B74: 6 | C74: apellidosConductor | D74: Apellidos y nombres del conductor (Apellidos) | E74: C | F74: an..250 | H74: /DespatchAdvice/cac:Shipment/cac:ShipmentStage/cac:DriverPerson/cbc:FamilyName | I74: /DespatchAdvice/cac:Shipment/cac:ShipmentStage/cac:DriverPerson/cbc:FamilyName
B75: 7 | C75: numLicenciaConducir | D75: Número de licencia de conducir | E75: C | F75: an..10 | H75: /DespatchAdvice/cac:Shipment/cac:ShipmentStage/cac:DriverPerson/cac:IdentityDocumentReference/cbc:ID | I75: /DespatchAdvice/cac:Shipment/cac:ShipmentStage/cac:DriverPerson/cac:IdentityDocumentReference/cbc:ID
B77: Archivo: Detalle (RRRRRRRRRRR-31-VXXX-999999999.PLL)
B78: Dirección del punto de partida
B79: Dirección del punto de llegada | H79: Partida | I79: Llegada
B80: 1 | D80: Primera columna de la fila TXT | E80: M | F80: an3 | G80: PLL
B81: 2 | C81: tipDireccionPartidaLlegada | D81: Tipo de direcciondel Punto: Partida / Llegada | G81: Partida Llegada
B82: 3 | C82: ubiPartidaLlegada | D82: Ubigeo de Partida / Llegada | E82: M | F82: an6 | G82: (Catálogo N° 13) | H82: /DespatchAdvice/cac:Shipment/cac:Delivery/cac:Despatch/cac:DespatchAddress/cbc:ID | I82: /DespatchAdvice/cac:Shipment/cac:Delivery/cac:DeliveryAddress/cbc:ID
B83: 4 | C83: dirPartidaLlegada | D83: Dirección completa y detallada de Partida / Llegada | E83: M | F83: an..500 | H83: /DespatchAdvice/cac:Shipment/cac:Delivery/cac:Despatch/cac:DespatchAddress/cac:AddressLine/cbc:Line | I83: /DespatchAdvice/cac:Shipment/cac:Delivery/cac:DeliveryAddress/cac:AddressLine/cbc:Line
B84: 5 | C84: longitudGeorreferenciaPartidaLlegada | D84: Punto de georreferencia de Partida / Llegada (Longitud) | E84: C | F84: an..13 | G84: n(3,8) | H84: /DespatchAdvice/cac:Shipment/cac:Delivery/cac:Despatch/cac:DespatchAddress/cac:LocationCoordinate/cbc:LatitudeDegreesMeasure | I84: /DespatchAdvice/cac:Shipment/cac:Delivery/cac:DeliveryAddress/cac:LocationCoordinate/cbc:LatitudeDegreesMeasure
B85: 6 | C85: latitudGeorreferenciaPartidaLlegada | D85: Punto de georreferencia de Partida / Llegada (Latitud) | E85: C | F85: an..13 | G85: n(3,8) | H85: /DespatchAdvice/cac:Shipment/cac:Delivery/cac:Despatch/cac:DespatchAddress/cac:LocationCoordinate/cbc:LongitudeDegreesMeasure | I85: /DespatchAdvice/cac:Shipment/cac:Delivery/cac:DeliveryAddress/cac:LocationCoordinate/cbc:LongitudeDegreesMeasure
B87: Archivo: Detalle (RRRRRRRRRRR-31-VXXX-999999999.BIE)
B88: Bienes a trasladar - Incremental
B89: 1 | D89: Primera columna de la fila TXT | E89: M | F89: an3 | G89: BIE
B90: 2 | C90: lineaBien | D90: Número de orden del item | E90: C | F90: n..4 | H90: /DespatchAdvice/cac:DespatchLine/cbc:ID
B91: 3 | C91: canBien | D91: Cantidad del bien | E91: C | F91: an..23 | G91: n(12,10) | H91: /DespatchAdvice/cac:DespatchLine/cbc:DeliveredQuantity
B92: 4 | C92: uniMedidaBien | D92: Unidad de medida del bien | E92: C | F92: an..3 | G92: (Catálogo N° 03) (Catálogo N° 65) | H92: /DespatchAdvice/cac:DespatchLine/cbc:DeliveredQuantity@unitCode
B93: 5 | C93: desItem | D93: Descripción detallada del bien | E93: C | F93: an..500 | H93: /DespatchAdvice/cac:DespatchLine/cac:Item/cbc:Description
B94: 6 | C94: codItem | D94: Código del bien | E94: C | F94: an..30 | H94: /DespatchAdvice/cac:DespatchLine/cac:Item/cac:SellersItemIdentification/cbc:ID
B95: 7 | C95: codProductoSunatItem | D95: Código producto SUNAT | E95: C | F95: n..8 | G95: (Catálogo N.° 25) | H95: /DespatchAdvice/cac:DespatchLine/cac:Item/cac:CommodityClassification/cbc:ItemClassificationCode
B96: 8 | C96: codProductoGTINItem | D96: Código de producto GTIN | E96: C | F96: an..14 | H96: /DespatchAdvice/cac:DespatchLine/cac:Item/cac:StandardItemIdentification/cbc:ID
B97: 9 | C97: tipEstructuraGTINItem | D97: Tipo de estructura GTIN | E97: C | G97: GTIN-8 GTIN-12 GTIN-13 GTIN-14 | H97: /DespatchAdvice/cac:DespatchLine/cac:Item/cac:StandardItemIdentification/cbc:ID@schemeID
B98: 10 | C98: nomConceptoItem | D98: Partida arancelaria Indicador de bien normalizado (Nombre del concepto) | E98: C | F98: an..100 | H98: /DespatchAdvice/cac:DespatchLine/cac:Item/cac:AdditionalItemProperty/cbc:Name
B99: 11 | C99: codConceptoItem | D99: Partida arancelaria Indicador de bien normalizado (Código del concepto) | E99: C | F99: an4 | G99: (Catálogo N.° 55) | H99: /DespatchAdvice/cac:DespatchLine/cac:Item/cac:AdditionalItemProperty/cbc:NameCode
B100: 12 | C100: valueItem | D100: Partida arancelaria | E100: C | F100: n..10 | H100: /DespatchAdvice/cac:DespatchLine/cac:Item/cac:AdditionalItemProperty/cbc:Value
D101: Indicador de bien normalizado | F101: n1 | G101: "0" Falso "1" Verdadero
B103: Archivo: Documento relacionado (RRRRRRRRRRR-31-VXXX-999999999.DOR)
B104: Documento relacionado - incremental
B105: 1 | D105: Primera columna de la fila TXT | E105: M | F105: an3 | G105: DOR
B106: 2 | C106: tipDocRel | D106: Tipo de documento (Descripción) | E106: C | F106: an..120 | H106: /DespatchAdvice/cac:AdditionalDocumentReference/cbc:DocumentType
B107: 3 | C107: codTipDocRel | D107: Código del tipo de documento relacionado | E107: C | F107: an2 | G107: (Catálogo N° 61) | H107: /DespatchAdvice/cac:AdditionalDocumentReference/cbc:DocumentTypeCode
B108: 4 | C108: numDocRel | D108: Número de documento relacionado | E108: C | F108: an..100 | H108: /DespatchAdvice/cac:AdditionalDocumentReference/cbc:ID
...

Sheet GRE-T-TXT
A1: 1 | B1: 2 | C1: 3 | D1: 4 | E1: 5 | F1: 6 | G1: 7 | H1: 8 | I1: 9 | J1: 10 | K1: 11 | L1: 12 | M1: 13 | N1: 14 | O1: 15 | P1: 16 | Q1: 17 | R1: 18
B2: nroCdpSwf | C2: fecEmision | D2: horEmision | E2: tipCdpSwf | F2: obsGuia | G2: tipDocuEmisorSwf | H2: nroRucEmisorSwf | I2: razonSocialSwf | J2: tipDocDestinatario | K2: numDocDestinatario | L2: rznSocialDestinatario | M2: tipDocSubcontratador | N2: numDocSubcontratador | O2: rznSocialSubcontratador | P2: tipDocPagaServicio | Q2: numDocPagaServicio | R2: rznSocialPagaServicio
A3: GRT
A6: 1 | B6: 2 | C6: 3 | D6: 4 | E6: 5 | F6: 6 | G6: 7 | H6: 8 | I6: 9 | J6: 10 | K6: 11 | L6: 12
B7: fecInicioTraslado | C7: anotacionOpcionalBienesTraslado | D7: psoBrutoTotalCargaTraslado | E7: uniMedidaPesoBrutoTraslado | F7: indTrasladoTotalBienes | G7: indRetornoVehiculoEnvasesEmbalajes | H7: indRetornoVehiculoVacio | I7: indTransbordoProgramado | J7: indTransporteSubcontratado | K7: indPagadorFlete | L7: tipEventoTraslado
A8: TSL
A11: 1 | B11: 2 | C11: 3 | D11: 4 | E11: 5 | F11: 6 | G11: 7
B12: tipDocTransportista | C12: numDocTransportista | D12: nomTransportista | E12: numeroRegistroMTCTransportista | F12: numAutorizacionTransportista | G12: codEntidadAutorizadoraTransportista
A13: TTA
A16: 1 | B16: 2 | C16: 3 | D16: 4 | E16: 5 | F16: 6
B17: tipVehiculo | C17: numPlacaVehículoPrincipal | D17: tarjetaUnicaCirculacionElecPrincipal | E17: numAutorizacionPrincipal | F17: codEntidadEmisoraPrincipal
A18: VPS | B18: Principal
A19: VPS | B19: Secundario
A21: 1 | B21: 2 | C21: 3 | D21: 4 | E21: 5 | F21: 6 | G21: 7
B22: tipConductor | C22: tipDocumentoConductor | D22: numDocumentoConductor | E22: nombresConductor | F22: apellidosConductor | G22: numLicenciaConducir
A23: CON | B23: Principal
A24: CON | B24: Secundario
A26: 1 | B26: 2 | C26: 3 | D26: 4 | E26: 5 | F26: 6
B27: tipDireccionPunto | C27: ubiPartida | D27: dirPartida | E27: longitudPuntoGeorreferenciaPartida | F27: latitudPuntoGeorreferenciaPartida
A28: PLL | B28: Partida
A29: PLL | B29: Llegada
A31: 1 | B31: 2 | C31: 3 | D31: 4 | E31: 5 | F31: 6 | G31: 7 | H31: 8 | I31: 9 | J31: 10 | K31: 11 | L31: 12
B32: lineaBien | C32: canBien | D32: uniMedidaBien | E32: desItem | F32: codItem | G32: codProductoSunatItem | H32: codProductoGTINItem | I32: tipEstructuraGTINItem | J32: nomConceptoItem | K32: codConceptoItem | L32: valueItem
A33: BIE
A36: 1 | B36: 2 | C36: 3 | D36: 4 | E36: 5 | F36: 6
B37: tipDocRel | C37: codTipDocRel | D37: numDocRel | E37: numDocEmisorDoc | F37: tipDocEmisorDocRel
A38: DOR

Sheet Catalogos
A1: Anexo V
A2: Anexo N.°8 : Catálogo de códigos
A4: No. | B4: 01
A5: Catálogo | B5: Código de tipo de documento
A6: Código | B6: Descripción
A7: 01 | B7: Factura
A8: 03 | B8: Boleta de venta
A9: 04 | B9: Liquidación de compra
A10: 05 | B10: Boletos de Transporte Aéreo que emiten las Compañías de Aviación Comercial por el servicio de transporte aéreo regular de pasajeros, emitido de manera manual, mecanizada o por medios electrónicos (BME)
A11: 06 | B11: Carta de porte aéreo
A12: 07 | B12: Nota de crédito
A13: 08 | B13: Nota de débito
A14: 09 | B14: Guía de remisión remitente
A15: 11 | B15: Póliza emitida por las Bolsas de Valores
A16: 12 | B16: Ticket de máquina registradora
A17: 13 | B17: Documento emitido por bancos, instituciones financieras, crediticias y de seguros que se encuentren bajo el control de la Superintendencia de Banca y Seguros
A18: 14 | B18: Recibo servicios públicos
A19: 15 | B19: Boletos emitidos por el servicio de transporte terrestre regular urbano de pasajeros y el ferroviario público de pasajeros prestado en vía férrea local
A20: 16 | B20: Boleto de viaje emitido por las empresas de transporte público interprovincial de pasajeros
A21: 18 | B21: Documentos emitidos por las AFP
A22: 19 | B22: Boleto por atracciones y espectáculos públicos
A23: 20 | B23: Comprobante de retención
A24: 21 | B24: Conocimiento de embarque por el servicio de transporte de carga marítima
A25: 23 | B25: Pólizas de Adjudicación por remate o adjudicación de bienes
A26: 24 | B26: Certificado de pago de regalías emitidas por PERUPETRO S.A.
A27: 28 | B27: Etiquetas por el pago de la Tarifa Unificada de Uso de Aeropuerto – TUUA
A28: 29 | B28: Documentos emitidos por la COFOPRI
A29: 30 | B29: Documentos emitidos por las empresas que desempeñan el rol adquirente en los sistemas de pago mediante tarjetas de crédito y débito, emitidas por bancos e instituciones financieras o crediticias, domiciliados o no en el país.
A30: 31 | B30: Guía de remisión transportista
A31: 32 | B31: Documentos emitidos por recaudadoras de la Garantía de Red Principal
A32: 34 | B32: Documento del Operador
A33: 35 | B33: Documento del Partícipe
A34: 36 | B34: Recibo de Distribución de Gas Natural
A35: 37 | B35: Documentos que emitan los concesionarios del servicio de revisiones técnicas
A36: 40 | B36: Comprobante de Percepción
A37: 41 | B37: Comprobante de Percepción – Venta interna ( físico - formato impreso)
A38: 42 | B38: Documentos emitidos por los adq. en los sistemas de pago por tarj. de crédito emitidas por ellas mismas
A39: 43 | B39: Boleto de compañías de aviación transporte aéreo no regular
A40: 45 | B40: Documentos emitidos por centros educativos y culturales, universidades, asociaciones y fundaciones
A41: 55 | B41: BVME para transporte ferroviario de pasajeros
A42: 56 | B42: Comprobante de pago SEAE
A43: 71 | B43: Guía de remisión remitente complementaria
A44: 72 | B44: Guía de remisión transportista complementaria
A45: 87 | B45: Nota de crédito especial
A46: 88 | B46: Nota de débito especial
A49: No. | B49: 03
A50: Catálogo | B50: Código de tipo de unidad de medida comercial
A51: Código | B51: Descripción
A52: UN/ECE Recommendation 20 Revision 13
A53: https://www.unece.org/fileadmin/DAM/uncefact/recommendations/rec20/rec20_Rev13e_2017.xls
A56: No. | B56: 06
A57: Catálogo | B57: Código de tipo de documento de identidad
A58: Código | B58: Descripción
A59: 0 | B59: DOC.TRIB.NO.DOM.SIN.RUC
A60: 1 | B60: Documento Nacional de Identidad
A61: 4 | B61: Carnet de extranjería
A62: 6 | B62: Registro Unico de Contributentes
A63: 7 | B63: Pasaporte
A64: A | B64: Cédula Diplomática de identidad
A65: B | B65: DOC.IDENT.PAIS.RESIDENCIA-NO.D
A66: C | B66: Tax Identification Number - TIN – Doc Trib PP.NN
A67: D | B67: Identification Number - IN – Doc Trib PP. JJ
... A75: Código | B75: Descripción
A76: Catálogo de ubigeos del INEI
A77: https://www.datosabiertos.gob.pe/dataset/c%C3%B3digo-de-ubicaci%C3%B3n-geogr%C3%A1fica-en-el-per%C3%BA-instituto-nacional-de-estad%C3%ADstica-e-inform%C3%A1tica
A80: No. | B80: 18
A81: Catálogo | B81: Código de modalidad de transporte
A82: Código | B82: Descripción
A83: 01 | B83: Transporte público
A84: 02 | B84: Transporte privado
A87: No. | B87: 20
A88: Catálogo | B88: Código de motivo de traslado
A89: Código | B89: Descripción
A90: 01 | B90: Venta
A91: 02 | B91: Compra
A92: 03 | B92: Venta con entrega a terceros
A93: 04 | B93: Traslado entre establecimientos de la misma empresa
... A100: 14 | B100: Venta sujeta a confirmación del comprador
A101: 17 | B101: Traslado de bienes para transformación
A102: 18 | B102: Traslado emisor itinerante CP
A105: No. | B105: 25
A106: Catálogo | B106: Código de producto SUNAT
A107: Código | B107: Descripción
A108: Sistema de Codificación Común de las Naciones Unidas - UNSPSC v14_0801 (nivel 3)
A109: https://www.unspsc.org/codeset-downloads/productid/28/createdbyuser/3?txtsearch=
A112: No. | B112: 52
A113: Catálogo | B113: Códigos de leyendas
A114: Código | B114: Descripción
A115: 1000 | B115: Monto en Letras
A116: 1002 | B116: Leyenda "TRANSFERENCIA GRATUITA DE UN BIEN Y/O SERVICIO PRESTADO GRATUITAMENTE"
A117: 2000 | B117: Leyenda “COMPROBANTE DE PERCEPCIÓN”
A118: 2001 | B118: Leyenda “BIENES TRANSFERIDOS EN LA AMAZONÍA REGIÓN SELVA PARA SER CONSUMIDOS EN LA MISMA"
A119: 2002 | B119: Leyenda “SERVICIOS PRESTADOS EN LA AMAZONÍA REGIÓN SELVA PARA SER CONSUMIDOS EN LA MISMA”
A120: 2003 | B120: Leyenda “CONTRATOS DE CONSTRUCCIÓN EJECUTADOS EN LA AMAZONÍA REGIÓN SELVA”
A121: 2004 | B121: Leyenda “Agencia de Viaje - Paquete turístico”
A122: 2005 | B122: Leyenda “Venta realizada por emisor itinerante”
A123: 2006 | B123: Leyenda "Operación sujeta a detracción"
A124: 2007 | B124: Leyenda "Operación sujeta al IVAP"
A125: 2008 | B125: Leyenda: “VENTA EXONERADA DEL IGV-ISC-IPM. PROHIBIDA LA VENTA FUERA DE LA ZONA COMERCIAL DE TACNA”
A126: 2009 | B126: Leyenda: “PRIMERA VENTA DE MERCANCÍA IDENTIFICABLE ENTRE USUARIOS DE LA ZONA COMERCIAL”
...

Sheet Codigos retorno
A1: Código | B1: Descripción de Error u Observación
A2: - | B2: -
A3: 0100 | B3: El sistema no puede responder su solicitud. Intente nuevamente o comuníquese con su Administrador
A4: 0101 | B4: El encabezado de seguridad es incorrecto
A5: 0102 | B5: Usuario o contrasena incorrectos
A6: 0103 | B6: El Usuario ingresado no existe
A7: 0104 | B7: La Clave ingresada es incorrecta
A8: 0105 | B8: El Usuario no está activo
A9: 0106 | B9: El Usuario no es válido
A10: 0109 | B10: El sistema no puede responder su solicitud. (El servicio de autenticación no está disponible)
A11: 0110 | B11: No se pudo obtener la informacion del tipo de usuario
A12: 0111 | B12: No tiene el perfil para enviar comprobantes electronicos
... A663: 2536 | B663: La serie y numero de la GRE consignada como documento relacionado no se encuentra registrado con baja por cambio de destinatario
A664: 2537 | B664: cac:OrderReference/cac:DocumentReference/cbc:DocumentTypeCode - El tipo de documento de serie y número dado de baja es incorrecta.
A665: 2538 | B665: El contribuyente no se encuentra autorizado como emisor electronico de Guía o de factura o de boletaFactura GEM.
A666: 2539 | B666: El contribuyente no esta activo.
A667: 2540 | B667: El contribuyente no esta habido.
A668: 2541 | B668: El XML no contiene el tag o no existe informacion del tipo de documento identidad del remitente.
A669: 2542 | B669: cac:DespatchSupplierParty/cbc:CustomerAssignedAccountID@schemeID - El valor ingresado como tipo de documento identidad del remitente es incorrecta.
A670: 2543 | B670: El XML no contiene el tag o no existe informacion de la dirección completa y detallada en domicilio fiscal.
A671: 2544 | B671: El XML no contiene el tag o no existe información de la provincia en domicilio fiscal.
A672: 2545 | B672: El XML no contiene el tag o no existe información del departamento en domicilio fiscal.
A673: 2546 | B673: El XML no contiene el tag o no existe información del distrito en domicilio fiscal.
A674: 2547 | B674: El XML no contiene el tag o no existe información del país en domicilio fiscal.
A675: 2548 | B675: El valor del país inválido.
A676: 2549 | B676: El XML no contiene el tag o no existe informacion del tipo de documento identidad del destinatario.
... A1980: 4437 | B1980: El control de los saldos pendientes de traslado es responsabilidad del contribuyente
